{"src":"https://docs.google.com/document/d/15rWfoHxCHXtWuRjZYYX6u98H9IG0U4AugsCEHDKzLas","id":"fbd9e173","name":"8o8keys","instagram":"https://www.instagram.com/8o8keys/","website":"","discord":"","selfOrder":false,"sculpts":[{"id":"e935253d","name":"TT v1","colorways":[{"name":"Graduation","img":"https://cdn.keycap-archivist.com/keycaps/9e2b6e8c.jpg","id":"9e2b6e8c","isCover":false,"note":""},{"name":"OG","img":"https://cdn.keycap-archivist.com/keycaps/5b64d9b6.jpg","id":"5b64d9b6","isCover":false,"note":""},{"name":"Grinch","img":"https://cdn.keycap-archivist.com/keycaps/e6b3ae00.jpg","id":"e6b3ae00","isCover":false,"note":""},{"name":"Taegeukgi","img":"https://cdn.keycap-archivist.com/keycaps/b05f67eb.jpg","id":"b05f67eb","isCover":false,"note":""},{"name":"Gateway","img":"https://cdn.keycap-archivist.com/keycaps/232d65a9.jpg","id":"232d65a9","isCover":false,"note":""},{"name":"Transparent V-day","img":"https://cdn.keycap-archivist.com/keycaps/3bab3313.jpg","id":"3bab3313","isCover":false,"note":""},{"name":"Cyberspace","img":"https://cdn.keycap-archivist.com/keycaps/bcc505b2.jpg","id":"bcc505b2","isCover":false,"note":""}]},{"id":"703c7487","name":"TT v2","colorways":[{"name":"Dead Presidents","img":"https://cdn.keycap-archivist.com/keycaps/6f5fb816.jpg","id":"6f5fb816","isCover":false,"note":""},{"name":"Flesh of my Flesh Blood of my Blood","img":"https://cdn.keycap-archivist.com/keycaps/8a4e9180.jpg","id":"8a4e9180","isCover":false,"note":""},{"name":"TTowelie","img":"https://cdn.keycap-archivist.com/keycaps/b8d300e6.jpg","id":"b8d300e6","isCover":false,"note":""},{"name":"TMNT","img":"https://cdn.keycap-archivist.com/keycaps/5912ad10.jpg","id":"5912ad10","isCover":false,"note":""},{"name":"Li Hing Apple","img":"https://cdn.keycap-archivist.com/keycaps/c7943785.jpg","id":"c7943785","isCover":false,"note":""},{"name":"Li Hing Lychee","img":"https://cdn.keycap-archivist.com/keycaps/82723ba1.jpg","id":"82723ba1","isCover":false,"note":""},{"name":"Li Hing Pineapple","img":"https://cdn.keycap-archivist.com/keycaps/3c140e59.jpg","id":"3c140e59","isCover":false,"note":""},{"name":"Drama Melpomene","img":"https://cdn.keycap-archivist.com/keycaps/15764a01.jpg","id":"15764a01","isCover":false,"note":""},{"name":"Drama Thalia","img":"https://cdn.keycap-archivist.com/keycaps/db46bcd8.jpg","id":"db46bcd8","isCover":false,"note":""},{"name":"Purps","img":"https://cdn.keycap-archivist.com/keycaps/756d9514.jpg","id":"756d9514","isCover":false,"note":""},{"name":"4 Lukas","img":"https://cdn.keycap-archivist.com/keycaps/afd310e0.jpg","id":"afd310e0","isCover":false,"note":""},{"name":"Isaac","img":"https://cdn.keycap-archivist.com/keycaps/d9555af5.jpg","id":"d9555af5","isCover":false,"note":""},{"name":"Sussy Baka","img":"https://cdn.keycap-archivist.com/keycaps/4ced56fc.jpg","id":"4ced56fc","isCover":false,"note":""},{"name":"PBS Space Time","img":"https://cdn.keycap-archivist.com/keycaps/7801365a.jpg","id":"7801365a","isCover":false,"note":""},{"name":"Houhai","img":"https://cdn.keycap-archivist.com/keycaps/cdc357dd.jpg","id":"cdc357dd","isCover":false,"note":""},{"name":"Pink Bean","img":"https://cdn.keycap-archivist.com/keycaps/7ebb2185.jpg","id":"7ebb2185","isCover":false,"note":""},{"name":"Orange Creamsicle","img":"https://cdn.keycap-archivist.com/keycaps/1e44b5ad.jpg","id":"1e44b5ad","isCover":false,"note":""},{"name":"Hi Dad Soup","img":"https://cdn.keycap-archivist.com/keycaps/80c9fa76.jpg","id":"80c9fa76","isCover":false,"note":""},{"name":"peepoLove","img":"https://cdn.keycap-archivist.com/keycaps/c08c77b5.jpg","id":"c08c77b5","isCover":false,"note":""},{"name":"Orichalcum","img":"https://cdn.keycap-archivist.com/keycaps/f32d85ad.jpg","id":"f32d85ad","isCover":false,"note":""},{"name":"Red M&M","img":"https://cdn.keycap-archivist.com/keycaps/bcae234f.jpg","id":"bcae234f","isCover":false,"note":""},{"name":"Yellow M&M","img":"https://cdn.keycap-archivist.com/keycaps/85dce0ec.jpg","id":"85dce0ec","isCover":false,"note":""},{"name":"Rudy","img":"https://cdn.keycap-archivist.com/keycaps/4cf07d39.jpg","id":"4cf07d39","isCover":false,"note":""},{"name":"CRYREX","img":"https://cdn.keycap-archivist.com/keycaps/353d28ef.jpg","id":"353d28ef","isCover":false,"note":""},{"name":"Hello KeyTT","img":"https://cdn.keycap-archivist.com/keycaps/7c9a4471.jpg","id":"7c9a4471","isCover":false,"note":""}]},{"id":"4980713d","name":"Brisé des Garçons","colorways":[{"name":"OG","img":"https://cdn.keycap-archivist.com/keycaps/59ef1c7.jpg","id":"59ef1c7","isCover":false,"note":""},{"name":"Dead Presidents","img":"https://cdn.keycap-archivist.com/keycaps/93ef6e4b.jpg","id":"93ef6e4b","isCover":false,"note":""},{"name":"Rainbow Road","img":"https://cdn.keycap-archivist.com/keycaps/a550b19.jpg","id":"a550b19","isCover":false,"note":""}]},{"id":"61a38b1b","name":"peepoLove","colorways":[{"name":"OG","img":"https://cdn.keycap-archivist.com/keycaps/c5928bb3.jpg","id":"c5928bb3","isCover":false,"note":""},{"name":"Transparent V-day","img":"https://cdn.keycap-archivist.com/keycaps/58d9006c.jpg","id":"58d9006c","isCover":false,"note":""},{"name":"Cyberspace","img":"https://cdn.keycap-archivist.com/keycaps/fd844067.jpg","id":"fd844067","isCover":false,"note":""},{"name":"Pau","img":"https://cdn.keycap-archivist.com/keycaps/c5551d83.jpg","id":"c5551d83","isCover":false,"note":""},{"name":"Pau Dead Eye","img":"https://cdn.keycap-archivist.com/keycaps/ae0009f.jpg","id":"ae0009f","isCover":false,"note":""},{"name":"OG Fulfillment","img":"https://cdn.keycap-archivist.com/keycaps/acec2a0e.jpg","id":"acec2a0e","isCover":false,"note":""},{"name":"Orichalcum","img":"https://cdn.keycap-archivist.com/keycaps/3fb7a4b9.jpg","id":"3fb7a4b9","isCover":false,"note":""},{"name":"D Lavender","img":"https://cdn.keycap-archivist.com/keycaps/bb877d15.jpg","id":"bb877d15","isCover":false,"note":""},{"name":"L Lavender","img":"https://cdn.keycap-archivist.com/keycaps/2d34167a.jpg","id":"2d34167a","isCover":false,"note":""}]},{"id":"3652b70b","name":"8o8xSleepy Sheepsomnia","colorways":[{"name":"sheepoLove","img":"https://cdn.keycap-archivist.com/keycaps/75b2c022.jpg","id":"75b2c022","isCover":false,"note":""},{"name":"Orichalcum","img":"https://cdn.keycap-archivist.com/keycaps/1772c9d8.jpg","id":"1772c9d8","isCover":false,"note":""}]}]}