{"src":"https://docs.google.com/document/d/18jTzayNzUDECKOfe-ZXa6oDucNj8_Pp0jEjsdzvvSws","id":"5137e37f","name":"KeyKollectiv","instagram":"https://www.instagram.com/keykollectiv/","website":"https://www.keykollectiv.com/","discord":"","sculpts":[{"id":"89c59f3c","name":"Meowcaps V1","colorways":[{"id":"73f99714","img":"https://cdn.keycap-archivist.com/keycaps/73f99714.jpg","name":"Master","isCover":false,"note":""},{"id":"397dbd5b","img":"https://cdn.keycap-archivist.com/keycaps/397dbd5b.jpg","name":"","isCover":false,"note":""},{"id":"4c0cc54c","img":"https://cdn.keycap-archivist.com/keycaps/4c0cc54c.jpg","name":"","isCover":false,"note":""},{"id":"bfab5360","img":"https://cdn.keycap-archivist.com/keycaps/bfab5360.jpg","name":"","isCover":false,"note":""},{"id":"6157f9d9","img":"https://cdn.keycap-archivist.com/keycaps/6157f9d9.jpg","name":"","isCover":false,"note":""},{"id":"3cb26b7","img":"https://cdn.keycap-archivist.com/keycaps/3cb26b7.jpg","name":"","isCover":false,"note":""},{"id":"9fefbe00","img":"https://cdn.keycap-archivist.com/keycaps/9fefbe00.jpg","name":"","isCover":false,"note":""},{"id":"334c6026","img":"https://cdn.keycap-archivist.com/keycaps/334c6026.jpg","name":"","isCover":false,"note":""},{"id":"a2a26541","img":"https://cdn.keycap-archivist.com/keycaps/a2a26541.jpg","name":"","isCover":false,"note":""},{"id":"5eed8b2","img":"https://cdn.keycap-archivist.com/keycaps/5eed8b2.jpg","name":"","isCover":false,"note":""},{"id":"989d7716","img":"https://cdn.keycap-archivist.com/keycaps/989d7716.jpg","name":"","isCover":false,"note":""},{"id":"5adac0a9","img":"https://cdn.keycap-archivist.com/keycaps/5adac0a9.jpg","name":"","isCover":false,"note":""},{"id":"60ec5203","img":"https://cdn.keycap-archivist.com/keycaps/60ec5203.jpg","name":"","isCover":false,"note":""},{"id":"2e10a5a7","img":"https://cdn.keycap-archivist.com/keycaps/2e10a5a7.jpg","name":"","isCover":false,"note":""},{"id":"5d1faa4d","img":"https://cdn.keycap-archivist.com/keycaps/5d1faa4d.jpg","name":"","isCover":false,"note":""},{"id":"15111713","img":"https://cdn.keycap-archivist.com/keycaps/15111713.jpg","name":"","isCover":false,"note":""},{"id":"28b68bad","img":"https://cdn.keycap-archivist.com/keycaps/28b68bad.jpg","name":"","isCover":false,"note":""},{"id":"2ffa1fb5","img":"https://cdn.keycap-archivist.com/keycaps/2ffa1fb5.jpg","name":"","isCover":false,"note":""}]},{"id":"10ccce86","name":"Meowcaps V2","colorways":[{"id":"e0890bb1","img":"https://cdn.keycap-archivist.com/keycaps/e0890bb1.jpg","name":"Artemis Black","isCover":false,"note":""},{"id":"19310ec4","img":"https://cdn.keycap-archivist.com/keycaps/19310ec4.jpg","name":"Strawberries and Cream","isCover":false,"note":""},{"id":"549ba64a","img":"https://cdn.keycap-archivist.com/keycaps/549ba64a.jpg","name":"Dusty Rose","isCover":false,"note":""},{"id":"3609ef07","img":"https://cdn.keycap-archivist.com/keycaps/3609ef07.jpg","name":"Latte","isCover":false,"note":""},{"id":"41a8db18","img":"https://cdn.keycap-archivist.com/keycaps/41a8db18.jpg","name":"Taro Milk","isCover":false,"note":""},{"id":"5de1910a","img":"https://cdn.keycap-archivist.com/keycaps/5de1910a.jpg","name":"Mint Chocolate","isCover":false,"note":""},{"id":"cc8a490f","img":"https://cdn.keycap-archivist.com/keycaps/cc8a490f.jpg","name":"Calico","isCover":false,"note":""},{"id":"1b0f2216","img":"https://cdn.keycap-archivist.com/keycaps/1b0f2216.jpg","name":"Pearl","isCover":false,"note":""}]},{"id":"67cbfe10","name":"Meowcaps V3","colorways":[{"id":"c4f15914","img":"https://cdn.keycap-archivist.com/keycaps/c4f15914.jpg","name":"Strawberry & Cream","isCover":false,"note":""},{"id":"e46f852","img":"https://cdn.keycap-archivist.com/keycaps/e46f852.jpg","name":"LeNoir","isCover":false,"note":""},{"id":"b210c69f","img":"https://cdn.keycap-archivist.com/keycaps/b210c69f.jpg","name":"MuteMeowlow","isCover":false,"note":""},{"id":"acc7c19","img":"https://cdn.keycap-archivist.com/keycaps/acc7c19.jpg","name":"Juicy","isCover":false,"note":""},{"id":"27956d49","img":"https://cdn.keycap-archivist.com/keycaps/27956d49.jpg","name":"Calico","isCover":false,"note":""},{"id":"cd863d1d","img":"https://cdn.keycap-archivist.com/keycaps/cd863d1d.jpg","name":"Exosphere","isCover":false,"note":""},{"id":"9522b886","img":"https://cdn.keycap-archivist.com/keycaps/9522b886.jpg","name":"","isCover":false,"note":""},{"id":"eacdef10","img":"https://cdn.keycap-archivist.com/keycaps/eacdef10.jpg","name":"Lina’s Kat","isCover":false,"note":""},{"id":"83c74b9d","img":"https://cdn.keycap-archivist.com/keycaps/83c74b9d.jpg","name":"Guava Beans","isCover":false,"note":""}]},{"id":"3526b2ba","name":"Snackeys Series 1 - Fruit","colorways":[{"id":"74b88446","img":"https://cdn.keycap-archivist.com/keycaps/74b88446.jpg","name":"Watermelon","isCover":false,"note":""},{"id":"582c6b46","img":"https://cdn.keycap-archivist.com/keycaps/582c6b46.jpg","name":"Kiwi","isCover":false,"note":""},{"id":"46e8fe45","img":"https://cdn.keycap-archivist.com/keycaps/46e8fe45.jpg","name":"Dragonfruit","isCover":false,"note":""},{"id":"4cf2fb9e","img":"https://cdn.keycap-archivist.com/keycaps/4cf2fb9e.jpg","name":"Boysenberry","isCover":false,"note":""},{"id":"a662442d","img":"https://cdn.keycap-archivist.com/keycaps/a662442d.jpg","name":"Coconut","isCover":false,"note":""},{"id":"e47324c8","img":"https://cdn.keycap-archivist.com/keycaps/e47324c8.jpg","name":"Blood Orange","isCover":false,"note":""},{"id":"3df99341","img":"https://cdn.keycap-archivist.com/keycaps/3df99341.jpg","name":"Strawberry","isCover":false,"note":""},{"id":"f94a1c29","img":"https://cdn.keycap-archivist.com/keycaps/f94a1c29.jpg","name":"Snozzberry","isCover":false,"note":""},{"id":"1504f474","img":"https://cdn.keycap-archivist.com/keycaps/1504f474.jpg","name":"Watermelon FN","isCover":false,"note":""},{"id":"81b0350b","img":"https://cdn.keycap-archivist.com/keycaps/81b0350b.jpg","name":"Dragonfruit FN","isCover":false,"note":""}]},{"id":"519faef8","name":"Snackeys Series 2 - Bento","colorways":[{"id":"22640bb8","img":"https://cdn.keycap-archivist.com/keycaps/22640bb8.jpg","name":"Sakura Sake","isCover":false,"note":""},{"id":"24641e5f","img":"https://cdn.keycap-archivist.com/keycaps/24641e5f.jpg","name":"Miso","isCover":false,"note":""},{"id":"181884f6","img":"https://cdn.keycap-archivist.com/keycaps/181884f6.jpg","name":"kiKKoman","isCover":false,"note":""},{"id":"96cbf8cc","img":"https://cdn.keycap-archivist.com/keycaps/96cbf8cc.jpg","name":"Sriracha","isCover":false,"note":""},{"id":"3b7e9d11","img":"https://cdn.keycap-archivist.com/keycaps/3b7e9d11.jpg","name":"Kappamaki","isCover":false,"note":""},{"id":"30c54a0d","img":"https://cdn.keycap-archivist.com/keycaps/30c54a0d.jpg","name":"Futomaki","isCover":false,"note":""},{"id":"871b9ee5","img":"https://cdn.keycap-archivist.com/keycaps/871b9ee5.jpg","name":"Tobiko (Roe)","isCover":false,"note":""},{"id":"b40ce2d7","img":"https://cdn.keycap-archivist.com/keycaps/b40ce2d7.jpg","name":"Hanami","isCover":false,"note":""},{"id":"8af4d0d8","img":"https://cdn.keycap-archivist.com/keycaps/8af4d0d8.jpg","name":"Wasabi","isCover":false,"note":""}]},{"id":"c7550059","name":"Snackeys Fruit Reboot","colorways":[{"id":"be9d92bb","img":"https://cdn.keycap-archivist.com/keycaps/be9d92bb.jpg","name":"Watermelon","isCover":false,"note":""},{"id":"9e28b022","img":"https://cdn.keycap-archivist.com/keycaps/9e28b022.jpg","name":"Strawberry","isCover":false,"note":""},{"id":"5cff756d","img":"https://cdn.keycap-archivist.com/keycaps/5cff756d.jpg","name":"Kiwi","isCover":false,"note":""},{"id":"1f3ab72c","img":"https://cdn.keycap-archivist.com/keycaps/1f3ab72c.jpg","name":"Snozzberry","isCover":false,"note":""},{"id":"be45d535","img":"https://cdn.keycap-archivist.com/keycaps/be45d535.jpg","name":"Blood Orange","isCover":false,"note":""},{"id":"8bc35be1","img":"https://cdn.keycap-archivist.com/keycaps/8bc35be1.jpg","name":"Boysenberry","isCover":false,"note":""},{"id":"fc13ae91","img":"https://cdn.keycap-archivist.com/keycaps/fc13ae91.jpg","name":"Dragonfruit","isCover":false,"note":""},{"id":"14bf4ce5","img":"https://cdn.keycap-archivist.com/keycaps/14bf4ce5.jpg","name":"Coconut","isCover":false,"note":""},{"id":"855db86b","img":"https://cdn.keycap-archivist.com/keycaps/855db86b.jpg","name":"Banana","isCover":false,"note":""},{"id":"90139f25","img":"https://cdn.keycap-archivist.com/keycaps/90139f25.jpg","name":"Pomengranate","isCover":false,"note":""},{"id":"e54d305","img":"https://cdn.keycap-archivist.com/keycaps/e54d305.jpg","name":"Pomegranate (Variant)","isCover":false,"note":""},{"id":"e1394b2c","img":"https://cdn.keycap-archivist.com/keycaps/e1394b2c.jpg","name":"Lychee","isCover":false,"note":""},{"id":"ec91ac2b","img":"https://cdn.keycap-archivist.com/keycaps/ec91ac2b.jpg","name":"BitBerry","isCover":false,"note":""},{"id":"cd10446a","img":"https://cdn.keycap-archivist.com/keycaps/cd10446a.jpg","name":"BitBerry Lite","isCover":false,"note":""},{"id":"3f50247b","img":"https://cdn.keycap-archivist.com/keycaps/3f50247b.jpg","name":"Sour Grape","isCover":false,"note":""}]},{"id":"3a200ba3","name":"Furt Beta","colorways":[{"id":"e6231d37","img":"https://cdn.keycap-archivist.com/keycaps/e6231d37.jpg","name":"Frozen Flame","isCover":false,"note":""},{"id":"86055588","img":"https://cdn.keycap-archivist.com/keycaps/86055588.jpg","name":"Furtive","isCover":false,"note":""},{"id":"3bc26b75","img":"https://cdn.keycap-archivist.com/keycaps/3bc26b75.jpg","name":"Bloodclot","isCover":false,"note":""},{"id":"7e50b4b3","img":"https://cdn.keycap-archivist.com/keycaps/7e50b4b3.jpg","name":"Juicy","isCover":false,"note":""},{"id":"a9c2d5d","img":"https://cdn.keycap-archivist.com/keycaps/a9c2d5d.jpg","name":"Forged","isCover":false,"note":""},{"id":"d8e4c489","img":"https://cdn.keycap-archivist.com/keycaps/d8e4c489.jpg","name":"Fallout","isCover":false,"note":""},{"id":"a228f7e5","img":"https://cdn.keycap-archivist.com/keycaps/a228f7e5.jpg","name":"Fallout (GID)","isCover":false,"note":""},{"id":"78ce4d1a","img":"https://cdn.keycap-archivist.com/keycaps/78ce4d1a.jpg","name":"Toilet","isCover":false,"note":""}]},{"id":"98186e84","name":"Furt Reborn","colorways":[{"id":"8a1d5079","img":"https://cdn.keycap-archivist.com/keycaps/8a1d5079.jpg","name":"Juicy","isCover":false,"note":""},{"id":"eeec1f43","img":"https://cdn.keycap-archivist.com/keycaps/eeec1f43.jpg","name":"Frozen Flame","isCover":false,"note":""},{"id":"db6c46ba","img":"https://cdn.keycap-archivist.com/keycaps/db6c46ba.jpg","name":"Furtive","isCover":false,"note":""},{"id":"269ed154","img":"https://cdn.keycap-archivist.com/keycaps/269ed154.jpg","name":"Bloodlust","isCover":false,"note":""},{"id":"8b56971d","img":"https://cdn.keycap-archivist.com/keycaps/8b56971d.jpg","name":"Exosphere","isCover":false,"note":""},{"id":"146885f5","img":"https://cdn.keycap-archivist.com/keycaps/146885f5.jpg","name":"Endosphere","isCover":false,"note":""},{"id":"ba51567e","img":"https://cdn.keycap-archivist.com/keycaps/ba51567e.jpg","name":"Dark Matter","isCover":false,"note":""},{"id":"b7106332","img":"https://cdn.keycap-archivist.com/keycaps/b7106332.jpg","name":"Bloodclot","isCover":false,"note":""},{"id":"6bfef95a","img":"https://cdn.keycap-archivist.com/keycaps/6bfef95a.jpg","name":"Fallout","isCover":false,"note":""}]},{"id":"a6a0978d","name":"Purrkeys","colorways":[{"id":"1aaa7f3e","img":"https://cdn.keycap-archivist.com/keycaps/1aaa7f3e.jpg","name":"Mr. Shankley","isCover":false,"note":""},{"id":"2618a76","img":"https://cdn.keycap-archivist.com/keycaps/2618a76.jpg","name":"Mao","isCover":false,"note":""},{"id":"5eec9bf4","img":"https://cdn.keycap-archivist.com/keycaps/5eec9bf4.jpg","name":"Lenore","isCover":false,"note":""},{"id":"168c5ee7","img":"https://cdn.keycap-archivist.com/keycaps/168c5ee7.jpg","name":"Rocco","isCover":false,"note":""},{"id":"4c28631b","img":"https://cdn.keycap-archivist.com/keycaps/4c28631b.jpg","name":"Schrodinger (GID)","isCover":false,"note":""},{"id":"fb4b9870","img":"https://cdn.keycap-archivist.com/keycaps/fb4b9870.jpg","name":"Schrodinger (GID)","isCover":false,"note":""},{"id":"bf9eff8b","img":"https://cdn.keycap-archivist.com/keycaps/bf9eff8b.jpg","name":"Mr. Bingley","isCover":false,"note":""},{"id":"c7bef990","img":"https://cdn.keycap-archivist.com/keycaps/c7bef990.jpg","name":"Latte","isCover":false,"note":""},{"id":"39bb42ff","img":"https://cdn.keycap-archivist.com/keycaps/39bb42ff.jpg","name":"Poof","isCover":false,"note":""}]},{"id":"7c91b963","name":"Key-Wala/Kill-Wala","colorways":[{"id":"896144aa","img":"https://cdn.keycap-archivist.com/keycaps/896144aa.jpg","name":"Marsupial Maroon","isCover":false,"note":""},{"id":"9e8550e","img":"https://cdn.keycap-archivist.com/keycaps/9e8550e.jpg","name":"Sour Marsupial Maroon","isCover":false,"note":""},{"id":"b5409e6f","img":"https://cdn.keycap-archivist.com/keycaps/b5409e6f.jpg","name":"Heisenberg Blue","isCover":false,"note":""},{"id":"773d80f7","img":"https://cdn.keycap-archivist.com/keycaps/773d80f7.jpg","name":"Sour Heisenberg Blue","isCover":false,"note":""},{"id":"a4555e9f","img":"https://cdn.keycap-archivist.com/keycaps/a4555e9f.jpg","name":"Purple Drank","isCover":false,"note":""},{"id":"f7739a16","img":"https://cdn.keycap-archivist.com/keycaps/f7739a16.jpg","name":"Sour Purple Drank","isCover":false,"note":""},{"id":"dff2fc","img":"https://cdn.keycap-archivist.com/keycaps/dff2fc.jpg","name":"Sunshine Yellow","isCover":false,"note":""},{"id":"aecf35ad","img":"https://cdn.keycap-archivist.com/keycaps/aecf35ad.jpg","name":"Sour Sunshine Yellow","isCover":false,"note":""},{"id":"e709e6b7","img":"https://cdn.keycap-archivist.com/keycaps/e709e6b7.jpg","name":"GatOrange","isCover":false,"note":""},{"id":"64dee1f6","img":"https://cdn.keycap-archivist.com/keycaps/64dee1f6.jpg","name":"Sour GatOrange","isCover":false,"note":""},{"id":"94ad907","img":"https://cdn.keycap-archivist.com/keycaps/94ad907.jpg","name":"Ecto-Cooler","isCover":false,"note":""},{"id":"d1cc814e","img":"https://cdn.keycap-archivist.com/keycaps/d1cc814e.jpg","name":"Sour Ecto-Cooler","isCover":false,"note":""},{"id":"7ab72817","img":"https://cdn.keycap-archivist.com/keycaps/7ab72817.jpg","name":"Sunburst Citrus","isCover":false,"note":""},{"id":"22c8ebaf","img":"https://cdn.keycap-archivist.com/keycaps/22c8ebaf.jpg","name":"Bermuda","isCover":false,"note":""},{"id":"fbfd03da","img":"https://cdn.keycap-archivist.com/keycaps/fbfd03da.jpg","name":"Exosphere","isCover":false,"note":""},{"id":"3f2c0c63","img":"https://cdn.keycap-archivist.com/keycaps/3f2c0c63.jpg","name":"Juicy","isCover":false,"note":""},{"id":"f9bebc0c","img":"https://cdn.keycap-archivist.com/keycaps/f9bebc0c.jpg","name":"Frozen Flame","isCover":false,"note":""},{"id":"9ef11c11","img":"https://cdn.keycap-archivist.com/keycaps/9ef11c11.jpg","name":"Bloodclot","isCover":false,"note":""},{"id":"581a3b68","img":"https://cdn.keycap-archivist.com/keycaps/581a3b68.jpg","name":"GID","isCover":false,"note":""},{"id":"c8aaac32","img":"https://cdn.keycap-archivist.com/keycaps/c8aaac32.jpg","name":"Spectral Blue","isCover":false,"note":""},{"id":"b803c07a","img":"https://cdn.keycap-archivist.com/keycaps/b803c07a.jpg","name":"Geist Green","isCover":false,"note":""}]},{"id":"cc1f685b","name":"Kosmonavt","colorways":[{"id":"33b1bb1","img":"https://cdn.keycap-archivist.com/keycaps/33b1bb1.jpg","name":"X15","isCover":false,"note":""},{"id":"d42c3dbd","img":"https://cdn.keycap-archivist.com/keycaps/d42c3dbd.jpg","name":"Watermelon","isCover":false,"note":""},{"id":"4fa3f930","img":"https://cdn.keycap-archivist.com/keycaps/4fa3f930.jpg","name":"Challenger","isCover":false,"note":""},{"id":"82c29f3a","img":"https://cdn.keycap-archivist.com/keycaps/82c29f3a.jpg","name":"Soyuz","isCover":false,"note":""},{"id":"c32f0b97","img":"https://cdn.keycap-archivist.com/keycaps/c32f0b97.jpg","name":"Columbia","isCover":false,"note":""},{"id":"8dc63c9b","img":"https://cdn.keycap-archivist.com/keycaps/8dc63c9b.jpg","name":"Voyager","isCover":false,"note":""},{"id":"f8bf5d7e","img":"https://cdn.keycap-archivist.com/keycaps/f8bf5d7e.jpg","name":"Apollo (GID)","isCover":false,"note":""},{"id":"216b948e","img":"https://cdn.keycap-archivist.com/keycaps/216b948e.jpg","name":"Gemini (GID)","isCover":false,"note":""},{"id":"13274ac7","img":"https://cdn.keycap-archivist.com/keycaps/13274ac7.jpg","name":"Codebreaker (Blue)","isCover":false,"note":""},{"id":"3df9b992","img":"https://cdn.keycap-archivist.com/keycaps/3df9b992.jpg","name":"LV426","isCover":false,"note":""},{"id":"c6b86ee0","img":"https://cdn.keycap-archivist.com/keycaps/c6b86ee0.jpg","name":"Pioneer","isCover":false,"note":""},{"id":"ae2782f9","img":"https://cdn.keycap-archivist.com/keycaps/ae2782f9.jpg","name":"Weyland Yutani","isCover":false,"note":""}]},{"id":"cad857ed","name":"Kosmonavt Reissue","colorways":[{"id":"2ab672e6","img":"https://cdn.keycap-archivist.com/keycaps/2ab672e6.jpg","name":"Challenger","isCover":false,"note":""},{"id":"f080bb78","img":"https://cdn.keycap-archivist.com/keycaps/f080bb78.jpg","name":"Columbia","isCover":false,"note":""},{"id":"6f722629","img":"https://cdn.keycap-archivist.com/keycaps/6f722629.jpg","name":"X15","isCover":false,"note":""},{"id":"70c7b68e","img":"https://cdn.keycap-archivist.com/keycaps/70c7b68e.jpg","name":"Soyuz","isCover":false,"note":""},{"id":"a533f6cf","img":"https://cdn.keycap-archivist.com/keycaps/a533f6cf.jpg","name":"Gemini (GID)","isCover":false,"note":""},{"id":"29ec03d6","img":"https://cdn.keycap-archivist.com/keycaps/29ec03d6.jpg","name":"Apollo (GID)","isCover":false,"note":""},{"id":"b57f12b8","img":"https://cdn.keycap-archivist.com/keycaps/b57f12b8.jpg","name":"Explorer (1/1)","isCover":false,"note":""},{"id":"d44e13ca","img":"https://cdn.keycap-archivist.com/keycaps/d44e13ca.jpg","name":"Sputnik (1/1)","isCover":false,"note":""},{"id":"305f6518","img":"https://cdn.keycap-archivist.com/keycaps/305f6518.jpg","name":"","isCover":false,"note":""},{"id":"28977abe","img":"https://cdn.keycap-archivist.com/keycaps/28977abe.jpg","name":"Event Horizon","isCover":false,"note":""},{"id":"3b609ee6","img":"https://cdn.keycap-archivist.com/keycaps/3b609ee6.jpg","name":"","isCover":false,"note":""}]},{"id":"49e049a6","name":"Frankenfurt","colorways":[{"id":"a24f5b5c","img":"https://cdn.keycap-archivist.com/keycaps/a24f5b5c.jpg","name":"Juicy","isCover":false,"note":""},{"id":"8de310e9","img":"https://cdn.keycap-archivist.com/keycaps/8de310e9.jpg","name":"Forged","isCover":false,"note":""},{"id":"4a85d23f","img":"https://cdn.keycap-archivist.com/keycaps/4a85d23f.jpg","name":"Frozen Flame","isCover":false,"note":""},{"id":"cd1d7bed","img":"https://cdn.keycap-archivist.com/keycaps/cd1d7bed.jpg","name":"Bloodlust","isCover":false,"note":""},{"id":"87c71126","img":"https://cdn.keycap-archivist.com/keycaps/87c71126.jpg","name":"Furtive","isCover":false,"note":""},{"id":"c0eed952","img":"https://cdn.keycap-archivist.com/keycaps/c0eed952.jpg","name":"Spectral/Geist","isCover":false,"note":""},{"id":"d8a18613","img":"https://cdn.keycap-archivist.com/keycaps/d8a18613.jpg","name":"Spectral (GID)","isCover":false,"note":""},{"id":"a3dcaa94","img":"https://cdn.keycap-archivist.com/keycaps/a3dcaa94.jpg","name":"Geist (GID)","isCover":false,"note":""},{"id":"815943a8","img":"https://cdn.keycap-archivist.com/keycaps/815943a8.jpg","name":"Hallowed (GID)","isCover":false,"note":""},{"id":"26e941ff","img":"https://cdn.keycap-archivist.com/keycaps/26e941ff.jpg","name":"Hallowed (GID)","isCover":false,"note":""},{"id":"f9643946","img":"https://cdn.keycap-archivist.com/keycaps/f9643946.jpg","name":"Prototype","isCover":false,"note":""}]},{"id":"db4e36d8","name":"Topre Mods","colorways":[{"id":"40d9ef1d","img":"https://cdn.keycap-archivist.com/keycaps/40d9ef1d.jpg","name":"Mtn Dew","isCover":false,"note":""},{"id":"47b96fdb","img":"https://cdn.keycap-archivist.com/keycaps/47b96fdb.jpg","name":"Spilled Purple Drank","isCover":false,"note":""},{"id":"78a3e0c2","img":"https://cdn.keycap-archivist.com/keycaps/78a3e0c2.jpg","name":"op8-Orange","isCover":false,"note":""},{"id":"74928382","img":"https://cdn.keycap-archivist.com/keycaps/74928382.jpg","name":"BTC-Blue","isCover":false,"note":""},{"id":"ff18d17f","img":"https://cdn.keycap-archivist.com/keycaps/ff18d17f.jpg","name":"Heliotrope","isCover":false,"note":""},{"id":"21fe5489","img":"https://cdn.keycap-archivist.com/keycaps/21fe5489.jpg","name":"CMYKeys","isCover":false,"note":""},{"id":"777e745","img":"https://cdn.keycap-archivist.com/keycaps/777e745.jpg","name":"","isCover":false,"note":""},{"id":"63af0755","img":"https://cdn.keycap-archivist.com/keycaps/63af0755.jpg","name":"Spectral Set (GID)","isCover":false,"note":""},{"id":"7e27e7d1","img":"https://cdn.keycap-archivist.com/keycaps/7e27e7d1.jpg","name":"","isCover":false,"note":""},{"id":"1c2b7d2c","img":"https://cdn.keycap-archivist.com/keycaps/1c2b7d2c.jpg","name":"Watermelon FN (Unseeded)","isCover":false,"note":""}]},{"id":"4a0c77c","name":"R1 Mods","colorways":[{"id":"501e7b68","img":"https://cdn.keycap-archivist.com/keycaps/501e7b68.jpg","name":"Triumphant Teal","isCover":false,"note":""},{"id":"656d267a","img":"https://cdn.keycap-archivist.com/keycaps/656d267a.jpg","name":"Bianchi Celeste Green","isCover":false,"note":""},{"id":"1fef960d","img":"https://cdn.keycap-archivist.com/keycaps/1fef960d.jpg","name":"Shallow Mallow","isCover":false,"note":""},{"id":"13b6f160","img":"https://cdn.keycap-archivist.com/keycaps/13b6f160.jpg","name":"Anniversary Blue","isCover":false,"note":""},{"id":"3e00b17c","img":"https://cdn.keycap-archivist.com/keycaps/3e00b17c.jpg","name":"Oxblood","isCover":false,"note":""},{"id":"5c4c40b8","img":"https://cdn.keycap-archivist.com/keycaps/5c4c40b8.jpg","name":"Pink Elephant","isCover":false,"note":""}]},{"id":"8234b5d2","name":"R2 Mods","colorways":[{"id":"540aa67c","img":"https://cdn.keycap-archivist.com/keycaps/540aa67c.jpg","name":"Mute-Mallow","isCover":false,"note":""},{"id":"15093f28","img":"https://cdn.keycap-archivist.com/keycaps/15093f28.jpg","name":"Sunset Sherbet","isCover":false,"note":""},{"id":"50de42cf","img":"https://cdn.keycap-archivist.com/keycaps/50de42cf.jpg","name":"Bubblegum Crisis Pink","isCover":false,"note":""},{"id":"6dcc19f9","img":"https://cdn.keycap-archivist.com/keycaps/6dcc19f9.jpg","name":"Oxblood","isCover":false,"note":""},{"id":"57b4bb78","img":"https://cdn.keycap-archivist.com/keycaps/57b4bb78.jpg","name":"Sacrificial Red","isCover":false,"note":""},{"id":"2ffa6909","img":"https://cdn.keycap-archivist.com/keycaps/2ffa6909.jpg","name":"Symbiosis Blue","isCover":false,"note":""},{"id":"cd9582e","img":"https://cdn.keycap-archivist.com/keycaps/cd9582e.jpg","name":"Bianchi Celeste","isCover":false,"note":""}]},{"id":"237d7096","name":"Miscellaneous","colorways":[{"id":"72f652a0","img":"https://cdn.keycap-archivist.com/keycaps/72f652a0.jpg","name":"Squll Squadron Master","isCover":false,"note":""},{"id":"964a500e","img":"https://cdn.keycap-archivist.com/keycaps/964a500e.jpg","name":"","isCover":false,"note":""},{"id":"1be5f7dc","img":"https://cdn.keycap-archivist.com/keycaps/1be5f7dc.jpg","name":"","isCover":false,"note":""},{"id":"9c66fa10","img":"https://cdn.keycap-archivist.com/keycaps/9c66fa10.jpg","name":"","isCover":false,"note":""},{"id":"f476f8c4","img":"https://cdn.keycap-archivist.com/keycaps/f476f8c4.jpg","name":"Chairman Meow","isCover":false,"note":""},{"id":"77152dfc","img":"https://cdn.keycap-archivist.com/keycaps/77152dfc.jpg","name":"Ghetto Blaster/Jukebox","isCover":false,"note":""},{"id":"79d05c18","img":"https://cdn.keycap-archivist.com/keycaps/79d05c18.jpg","name":"","isCover":false,"note":""},{"id":"e73f5b26","img":"https://cdn.keycap-archivist.com/keycaps/e73f5b26.jpg","name":"","isCover":false,"note":""}]},{"id":"36551355","name":"Accessories","colorways":[{"id":"1259cb26","img":"https://cdn.keycap-archivist.com/keycaps/1259cb26.jpg","name":"(Comes in many flavors)","isCover":false,"note":""},{"id":"b4350875","img":"https://cdn.keycap-archivist.com/keycaps/b4350875.jpg","name":"","isCover":false,"note":""},{"id":"e8dd4534","img":"https://cdn.keycap-archivist.com/keycaps/e8dd4534.jpg","name":"OG Furt Keychain","isCover":false,"note":""},{"id":"20087af9","img":"https://cdn.keycap-archivist.com/keycaps/20087af9.jpg","name":"MomKollectiv Sleeve","isCover":false,"note":""},{"id":"7b616a16","img":"https://cdn.keycap-archivist.com/keycaps/7b616a16.jpg","name":"Nigiri Keychain","isCover":false,"note":""},{"id":"c26f330","img":"https://cdn.keycap-archivist.com/keycaps/c26f330.jpg","name":"Furt-Melon Keychain","isCover":false,"note":""},{"id":"53ed7a0a","img":"https://cdn.keycap-archivist.com/keycaps/53ed7a0a.jpg","name":"Watermelon Sleeve","isCover":false,"note":""},{"id":"4fbb493b","img":"https://cdn.keycap-archivist.com/keycaps/4fbb493b.jpg","name":"Furt Reborn Keychain (Reversible)","isCover":false,"note":""},{"id":"200b6e3a","img":"https://cdn.keycap-archivist.com/keycaps/200b6e3a.jpg","name":"Spring Fling Furt Keychain","isCover":false,"note":""},{"id":"1659e110","img":"https://cdn.keycap-archivist.com/keycaps/1659e110.jpg","name":"Spring Fling Furt Sleeve","isCover":false,"note":""}]}],"artisanCollector":"https://artisancollector.com/keykollectiv/","selfOrder":false}