{"src":"https://docs.google.com/document/d/1ceCQ48nyCfZ2u0jnzgnvVW0nuxd01a0QS48cx_TVh-U","id":"f79138dd","name":"MelonKeys","instagram":"https://www.instagram.com/melonkeys.keycaps","website":"https://www.melonkeys.com","discord":"https://discord.gg/melonkeys","sculpts":[{"id":"68e07c7e","name":"Rush","colorways":[{"id":"80f80478","img":"https://cdn.keycap-archivist.com/keycaps/80f80478.jpg","name":"Eva-01","isCover":false,"releaseDate":"July 2023","note":""},{"id":"c0f1519f","img":"https://cdn.keycap-archivist.com/keycaps/c0f1519f.jpg","name":"Buzz","isCover":false,"releaseDate":"July 2023","note":""},{"id":"aaab1c0b","img":"https://cdn.keycap-archivist.com/keycaps/aaab1c0b.jpg","name":"OG","isCover":false,"releaseDate":"July 2023","note":""},{"id":"45610e61","img":"https://cdn.keycap-archivist.com/keycaps/45610e61.jpg","name":"Pakkun","isCover":false,"releaseDate":"July 2023","note":""},{"id":"33b1c05a","img":"https://cdn.keycap-archivist.com/keycaps/33b1c05a.jpg","name":"Dorae","isCover":false,"releaseDate":"Aug 2023","note":""},{"id":"7d0bbbd7","img":"https://cdn.keycap-archivist.com/keycaps/7d0bbbd7.jpg","name":"No Face","isCover":false,"releaseDate":"Oct 2023","note":""}]},{"id":"5cb3f9e6","name":"Battle Kid","colorways":[{"id":"25fbc911","img":"https://cdn.keycap-archivist.com/keycaps/25fbc911.jpg","name":"Eva-01","isCover":false,"releaseDate":"July 2023","note":""},{"id":"d1695f58","img":"https://cdn.keycap-archivist.com/keycaps/d1695f58.jpg","name":"Buzz","isCover":false,"releaseDate":"July 2023","note":""},{"id":"bb248e7","img":"https://cdn.keycap-archivist.com/keycaps/bb248e7.jpg","name":"OG","isCover":false,"releaseDate":"July 2023","note":""},{"id":"b8d63aa6","img":"https://cdn.keycap-archivist.com/keycaps/b8d63aa6.jpg","name":"Kakashi","isCover":false,"releaseDate":"July 2023","note":""},{"id":"5ec8eefe","img":"https://cdn.keycap-archivist.com/keycaps/5ec8eefe.jpg","name":"Dorae","isCover":false,"releaseDate":"Aug 2023","note":""},{"id":"64ec8f08","img":"https://cdn.keycap-archivist.com/keycaps/64ec8f08.jpg","name":"No Face","isCover":false,"releaseDate":"Oct 2023","note":""}]},{"id":"775acdf8","name":"Dragon","colorways":[{"id":"94558092","img":"https://cdn.keycap-archivist.com/keycaps/94558092.jpg","name":"Blue-Eyes White Dragon","isCover":false,"releaseDate":"Feb 2024","note":""}]},{"id":"951cefec","name":"R.Sensei","colorways":[{"id":"d3dafb60","img":"https://cdn.keycap-archivist.com/keycaps/d3dafb60.jpg","name":"10 Billion Percent","isCover":false,"releaseDate":"Sep 2022","totalCount":"25","note":""},{"id":"b7cccd89","img":"https://cdn.keycap-archivist.com/keycaps/b7cccd89.jpg","name":"OG","isCover":false,"releaseDate":"Oct 2022","totalCount":"10","note":""},{"id":"1d41f83f","img":"https://cdn.keycap-archivist.com/keycaps/1d41f83f.jpg","name":"Perv AF OG","isCover":false,"giveaway":true,"note":""},{"id":"64c5f5ee","img":"https://cdn.keycap-archivist.com/keycaps/64c5f5ee.jpg","name":"Namekian","isCover":false,"releaseDate":"Jan 2023","note":""}]},{"id":"624ea85c","name":"Blasé","colorways":[{"id":"4ddcb656","img":"https://cdn.keycap-archivist.com/keycaps/4ddcb656.jpg","name":"JL Batman","isCover":false,"releaseDate":"Apr 2023","totalCount":"15","note":""},{"id":"c2169322","img":"https://cdn.keycap-archivist.com/keycaps/c2169322.jpg","name":"JL Cyborg","isCover":false,"releaseDate":"Apr 2023","totalCount":"15","note":""},{"id":"404da6b5","img":"https://cdn.keycap-archivist.com/keycaps/404da6b5.jpg","name":"JL Green Lantern","isCover":false,"releaseDate":"Apr 2023","totalCount":"15","note":""},{"id":"16d8ee1a","img":"https://cdn.keycap-archivist.com/keycaps/16d8ee1a.jpg","name":"JL Superman","isCover":false,"releaseDate":"Apr 2023","totalCount":"15","note":""},{"id":"e1ef62f4","img":"https://cdn.keycap-archivist.com/keycaps/e1ef62f4.jpg","name":"JL The Flash","isCover":false,"releaseDate":"Apr 2023","totalCount":"15","note":""},{"id":"4661d6b5","img":"https://cdn.keycap-archivist.com/keycaps/4661d6b5.jpg","name":"Nanaba","isCover":false,"releaseDate":"May 2023","note":""},{"id":"b31a119c","img":"https://cdn.keycap-archivist.com/keycaps/b31a119c.jpg","name":"Demonic","isCover":false,"releaseDate":"May 2023","note":""},{"id":"8d27eee6","img":"https://cdn.keycap-archivist.com/keycaps/8d27eee6.jpg","name":"Witch","isCover":false,"releaseDate":"May 2023","note":""}]},{"id":"d2ca7581","name":"Exodia","colorways":[{"id":"d399af9","img":"https://cdn.keycap-archivist.com/keycaps/d399af9.jpg","name":"The Forbidden One","isCover":false,"releaseDate":"May 2023","note":""},{"id":"5834623","img":"https://cdn.keycap-archivist.com/keycaps/5834623.jpg","name":"Horus","isCover":false,"releaseDate":"May 2023","note":""},{"id":"82f816c4","img":"https://cdn.keycap-archivist.com/keycaps/82f816c4.jpg","name":"Anubis","isCover":false,"releaseDate":"May 2023","note":""},{"id":"f12a96f3","img":"https://cdn.keycap-archivist.com/keycaps/f12a96f3.jpg","name":"Hathor","isCover":false,"releaseDate":"May 2023","note":""},{"id":"ca121619","img":"https://cdn.keycap-archivist.com/keycaps/ca121619.jpg","name":"Roxy","isCover":false,"releaseDate":"Jun 2023","note":""},{"id":"9a3d8174","img":"https://cdn.keycap-archivist.com/keycaps/9a3d8174.jpg","name":"Hazakura","isCover":false,"releaseDate":"July 2023","note":""},{"id":"3a322274","img":"https://cdn.keycap-archivist.com/keycaps/3a322274.jpg","name":"Necross","isCover":false,"releaseDate":"July 2023","note":""}]},{"id":"698be0c2","name":"SS DMG","colorways":[{"id":"44fb5244","img":"https://cdn.keycap-archivist.com/keycaps/44fb5244.jpg","name":"Kakashi","isCover":false,"releaseDate":"Jul 2022","note":""},{"id":"89e8d151","img":"https://cdn.keycap-archivist.com/keycaps/89e8d151.jpg","name":"Rin","isCover":false,"releaseDate":"Jul 2022","totalCount":"25","note":""},{"id":"ffa30bab","img":"https://cdn.keycap-archivist.com/keycaps/ffa30bab.jpg","name":"Kiwi","isCover":false,"releaseDate":"Aug 2022","totalCount":"25","note":""},{"id":"3a4365d6","img":"https://cdn.keycap-archivist.com/keycaps/3a4365d6.jpg","name":"Distinguished","isCover":false,"releaseDate":"Sep 2022","totalCount":"25","note":""},{"id":"f218ef0a","img":"https://cdn.keycap-archivist.com/keycaps/f218ef0a.jpg","name":"Shelter","isCover":false,"releaseDate":"Sep 2022","totalCount":"25","note":""},{"id":"e5db2de","img":"https://cdn.keycap-archivist.com/keycaps/e5db2de.jpg","name":"10 Billion Percent","isCover":false,"releaseDate":"Sep 2022","totalCount":"25","note":""},{"id":"96d196ae","img":"https://cdn.keycap-archivist.com/keycaps/96d196ae.jpg","name":"Magi Magi","isCover":false,"releaseDate":"Sep 2022","totalCount":"25","note":""},{"id":"3c19603e","img":"https://cdn.keycap-archivist.com/keycaps/3c19603e.jpg","name":"Chock","isCover":false,"releaseDate":"Oct 2022","totalCount":"25","note":""},{"id":"de97b51a","img":"https://cdn.keycap-archivist.com/keycaps/de97b51a.jpg","name":"Heart Beat","isCover":false,"releaseDate":"Oct 2022","totalCount":"25","note":""},{"id":"e5aba06b","img":"https://cdn.keycap-archivist.com/keycaps/e5aba06b.jpg","name":"Rem","isCover":false,"releaseDate":"Dec 2022","totalCount":"25","note":""},{"id":"efb66775","img":"https://cdn.keycap-archivist.com/keycaps/efb66775.jpg","name":"Ram","isCover":false,"releaseDate":"Dec 2022","totalCount":"25","note":""},{"id":"31c2eacd","img":"https://cdn.keycap-archivist.com/keycaps/31c2eacd.jpg","name":"Emilia","isCover":false,"releaseDate":"Dec 2022","totalCount":"25","note":""},{"id":"5346e2e5","img":"https://cdn.keycap-archivist.com/keycaps/5346e2e5.jpg","name":"Doom Bringers","isCover":false,"releaseDate":"Dec 2022","totalCount":"25","note":""},{"id":"310dc0de","img":"https://cdn.keycap-archivist.com/keycaps/310dc0de.jpg","name":"The Grid","isCover":false,"releaseDate":"Dec 2022","totalCount":"25","note":""},{"id":"d5c14bc9","img":"https://cdn.keycap-archivist.com/keycaps/d5c14bc9.jpg","name":"Mario","isCover":false,"releaseDate":"Dec 2022","totalCount":"25","note":""},{"id":"fa0b45e7","img":"https://cdn.keycap-archivist.com/keycaps/fa0b45e7.jpg","name":"Spectre","isCover":false,"releaseDate":"Dec 2022","totalCount":"25","note":""},{"id":"bc987e6c","img":"https://cdn.keycap-archivist.com/keycaps/bc987e6c.jpg","name":"Makku","isCover":false,"releaseDate":"Dec 2022","totalCount":"10","note":""},{"id":"4c279a26","img":"https://cdn.keycap-archivist.com/keycaps/4c279a26.jpg","name":"Pastel","isCover":false,"releaseDate":"Dec 2022","totalCount":"25","note":""},{"id":"2d6e5838","img":"https://cdn.keycap-archivist.com/keycaps/2d6e5838.jpg","name":"Berry","isCover":false,"releaseDate":"Dec 2022","totalCount":"25","note":""},{"id":"cb0e7a9b","img":"https://cdn.keycap-archivist.com/keycaps/cb0e7a9b.jpg","name":"Lemon","isCover":false,"releaseDate":"Jan 2023","totalCount":"25","note":""},{"id":"1154c737","img":"https://cdn.keycap-archivist.com/keycaps/1154c737.jpg","name":"Bakugo","isCover":false,"releaseDate":"Feb 2023","totalCount":"25","note":""},{"id":"8063ec11","img":"https://cdn.keycap-archivist.com/keycaps/8063ec11.jpg","name":"Tartarus","isCover":false,"releaseDate":"Feb 2023","totalCount":"25","note":""},{"id":"6ee25b58","img":"https://cdn.keycap-archivist.com/keycaps/6ee25b58.jpg","name":"Calculated","isCover":false,"releaseDate":"Feb 2023","totalCount":"25","note":""},{"id":"76ae980b","img":"https://cdn.keycap-archivist.com/keycaps/76ae980b.jpg","name":"Illusion","isCover":false,"releaseDate":"Mar 2023","totalCount":"25","note":""}]},{"id":"82484cf2","name":"SS DM","colorways":[{"id":"409864c1","img":"https://cdn.keycap-archivist.com/keycaps/409864c1.jpg","name":"Obito","isCover":false,"releaseDate":"Jul 2022","totalCount":"25","note":""},{"id":"56a46dd5","img":"https://cdn.keycap-archivist.com/keycaps/56a46dd5.jpg","name":"Ancient Frost","isCover":false,"releaseDate":"Aug 2022","totalCount":"15","note":""},{"id":"dfae77b5","img":"https://cdn.keycap-archivist.com/keycaps/dfae77b5.jpg","name":"Jigsaw","isCover":false,"releaseDate":"Aug 2022","totalCount":"15","note":""},{"id":"d66c21b8","img":"https://cdn.keycap-archivist.com/keycaps/d66c21b8.jpg","name":"Vivi","isCover":false,"releaseDate":"Aug 2022","totalCount":"15","note":""},{"id":"26750b35","img":"https://cdn.keycap-archivist.com/keycaps/26750b35.jpg","name":"Bucky","isCover":false,"releaseDate":"Aug 2022","totalCount":"15","note":""},{"id":"175a12ca","img":"https://cdn.keycap-archivist.com/keycaps/175a12ca.jpg","name":"Kaito Kid","isCover":false,"releaseDate":"Aug 2022","totalCount":"15","note":""},{"id":"40eec833","img":"https://cdn.keycap-archivist.com/keycaps/40eec833.jpg","name":"Kiwi","isCover":false,"releaseDate":"Aug 2022","totalCount":"25","note":""},{"id":"10640120","img":"https://cdn.keycap-archivist.com/keycaps/10640120.jpg","name":"Distinguished","isCover":false,"releaseDate":"Sep 2022","totalCount":"25","note":""},{"id":"5dd5af3c","img":"https://cdn.keycap-archivist.com/keycaps/5dd5af3c.jpg","name":"Shelter","isCover":false,"releaseDate":"Sep 2022","totalCount":"25","note":""},{"id":"25447ab6","img":"https://cdn.keycap-archivist.com/keycaps/25447ab6.jpg","name":"10 Billion Percent","isCover":false,"releaseDate":"Sep 2022","totalCount":"25","note":""},{"id":"5e3c7d92","img":"https://cdn.keycap-archivist.com/keycaps/5e3c7d92.jpg","name":"Magi Magi","isCover":false,"releaseDate":"Sep 2022","totalCount":"25","note":""},{"id":"88efae7b","img":"https://cdn.keycap-archivist.com/keycaps/88efae7b.jpg","name":"Chock","isCover":false,"releaseDate":"Oct 2022","totalCount":"25","note":""},{"id":"a355b3cb","img":"https://cdn.keycap-archivist.com/keycaps/a355b3cb.jpg","name":"Heart Beat","isCover":false,"releaseDate":"Oct 2022","totalCount":"25","note":""},{"id":"724b50ed","img":"https://cdn.keycap-archivist.com/keycaps/724b50ed.jpg","name":"Rem","isCover":false,"releaseDate":"Nov 2022","totalCount":"25","note":""},{"id":"cf3dc951","img":"https://cdn.keycap-archivist.com/keycaps/cf3dc951.jpg","name":"Ram","isCover":false,"releaseDate":"Nov 2022","totalCount":"25","note":""},{"id":"b983fdcb","img":"https://cdn.keycap-archivist.com/keycaps/b983fdcb.jpg","name":"Emilia","isCover":false,"releaseDate":"Nov 2022","totalCount":"25","note":""},{"id":"8f923e97","img":"https://cdn.keycap-archivist.com/keycaps/8f923e97.jpg","name":"Doom Bringers","isCover":false,"releaseDate":"Dec 2022","totalCount":"25","note":""},{"id":"e15c7e4","img":"https://cdn.keycap-archivist.com/keycaps/e15c7e4.jpg","name":"The Grid","isCover":false,"releaseDate":"Dec 2022","totalCount":"25","note":""},{"id":"a3debff8","img":"https://cdn.keycap-archivist.com/keycaps/a3debff8.jpg","name":"Peach","isCover":false,"releaseDate":"Dec 2022","totalCount":"25","note":""},{"id":"fef38caf","img":"https://cdn.keycap-archivist.com/keycaps/fef38caf.jpg","name":"Spectre","isCover":false,"releaseDate":"Dec 2022","totalCount":"25","note":""},{"id":"cad96d04","img":"https://cdn.keycap-archivist.com/keycaps/cad96d04.jpg","name":"Makku","isCover":false,"releaseDate":"Dec 2022","totalCount":"10","note":""},{"id":"d598a29a","img":"https://cdn.keycap-archivist.com/keycaps/d598a29a.jpg","name":"Pastel","isCover":false,"releaseDate":"Dec 2022","totalCount":"25","note":""},{"id":"d83bc94","img":"https://cdn.keycap-archivist.com/keycaps/d83bc94.jpg","name":"Berry","isCover":false,"releaseDate":"Dec 2022","totalCount":"25","note":""},{"id":"80301d29","img":"https://cdn.keycap-archivist.com/keycaps/80301d29.jpg","name":"Lemon","isCover":false,"releaseDate":"Jan 2023","totalCount":"25","note":""},{"id":"f11ebcb","img":"https://cdn.keycap-archivist.com/keycaps/f11ebcb.jpg","name":"Bakugo","isCover":false,"releaseDate":"Feb 2023","totalCount":"25","note":""},{"id":"199143f8","img":"https://cdn.keycap-archivist.com/keycaps/199143f8.jpg","name":"Tartarus","isCover":false,"releaseDate":"Feb 2023","totalCount":"25","note":""},{"id":"b43d796e","img":"https://cdn.keycap-archivist.com/keycaps/b43d796e.jpg","name":"Calculated","isCover":false,"releaseDate":"Feb 2023","totalCount":"25","note":""},{"id":"c2a69b88","img":"https://cdn.keycap-archivist.com/keycaps/c2a69b88.jpg","name":"Illusion","isCover":false,"releaseDate":"Mar 2023","totalCount":"25","note":""},{"id":"4f698928","img":"https://cdn.keycap-archivist.com/keycaps/4f698928.jpg","name":"Gawr Gura","isCover":false,"releaseDate":"Mar 2023","note":""},{"id":"6c663cf2","img":"https://cdn.keycap-archivist.com/keycaps/6c663cf2.jpg","name":"OG Reversed","isCover":false,"releaseDate":"Mar 2023","note":""},{"id":"1e0e41a5","img":"https://cdn.keycap-archivist.com/keycaps/1e0e41a5.jpg","name":"Euler","isCover":false,"releaseDate":"Apr 2023","note":""},{"id":"e5fd0f4","img":"https://cdn.keycap-archivist.com/keycaps/e5fd0f4.jpg","name":"Dark Melon","isCover":false,"releaseDate":"Apr 2023","note":""},{"id":"1bfcb5be","img":"https://cdn.keycap-archivist.com/keycaps/1bfcb5be.jpg","name":"Team Rocket: James","isCover":false,"releaseDate":"Apr 2023","note":""},{"id":"6027f4c","img":"https://cdn.keycap-archivist.com/keycaps/6027f4c.jpg","name":"Kaiju","isCover":false,"releaseDate":"Apr 2023","note":""},{"id":"7d22abcb","img":"https://cdn.keycap-archivist.com/keycaps/7d22abcb.jpg","name":"Copper","isCover":false,"releaseDate":"May 2023","note":""},{"id":"58ee4099","img":"https://cdn.keycap-archivist.com/keycaps/58ee4099.jpg","name":"Nanaba","isCover":false,"releaseDate":"May 2023","note":""},{"id":"558d78ca","img":"https://cdn.keycap-archivist.com/keycaps/558d78ca.jpg","name":"Yun","isCover":false,"releaseDate":"Jun 2023","note":""},{"id":"6949191f","img":"https://cdn.keycap-archivist.com/keycaps/6949191f.jpg","name":"Xing","isCover":false,"releaseDate":"Jun 2023","note":""},{"id":"5eae595a","img":"https://cdn.keycap-archivist.com/keycaps/5eae595a.jpg","name":"Genos","isCover":false,"releaseDate":"Jun 2023","note":""},{"id":"a835d8ab","img":"https://cdn.keycap-archivist.com/keycaps/a835d8ab.jpg","name":"Mictlán","isCover":false,"releaseDate":"Jun 2023","note":""},{"id":"846a32a4","img":"https://cdn.keycap-archivist.com/keycaps/846a32a4.jpg","name":"Darling","isCover":false,"releaseDate":"Jun 2023","note":""},{"id":"fa2192c2","img":"https://cdn.keycap-archivist.com/keycaps/fa2192c2.jpg","name":"Roxy","isCover":false,"releaseDate":"Jun 2023","note":""},{"id":"c8e2972d","img":"https://cdn.keycap-archivist.com/keycaps/c8e2972d.jpg","name":"Hazakura","isCover":false,"releaseDate":"July 2023","note":""},{"id":"bf08f384","img":"https://cdn.keycap-archivist.com/keycaps/bf08f384.jpg","name":"Buzz","isCover":false,"releaseDate":"July 2023","note":""},{"id":"b929df35","img":"https://cdn.keycap-archivist.com/keycaps/b929df35.jpg","name":"Summer","isCover":false,"releaseDate":"July 2023","note":""},{"id":"72bba87","img":"https://cdn.keycap-archivist.com/keycaps/72bba87.jpg","name":"Necross","isCover":false,"releaseDate":"July 2023","note":""},{"id":"910c95ba","img":"https://cdn.keycap-archivist.com/keycaps/910c95ba.jpg","name":"Inuyasha","isCover":false,"releaseDate":"July 2023","note":""},{"id":"16e648f","img":"https://cdn.keycap-archivist.com/keycaps/16e648f.jpg","name":"Reaper","isCover":false,"releaseDate":"Aug 2023","note":""},{"id":"67faba6e","img":"https://cdn.keycap-archivist.com/keycaps/67faba6e.jpg","name":"EVA-02","isCover":false,"releaseDate":"Aug 2023","note":""},{"id":"97fb008a","img":"https://cdn.keycap-archivist.com/keycaps/97fb008a.jpg","name":"Kill la Kill","isCover":false,"releaseDate":"Sep 2023","note":""},{"id":"d0e765fe","img":"https://cdn.keycap-archivist.com/keycaps/d0e765fe.jpg","name":"Nahida","isCover":false,"releaseDate":"Sep 2023","note":""},{"id":"4f670be2","img":"https://cdn.keycap-archivist.com/keycaps/4f670be2.jpg","name":"Nier","isCover":false,"releaseDate":"Sep 2023","note":""},{"id":"e0102acc","img":"https://cdn.keycap-archivist.com/keycaps/e0102acc.jpg","name":"Lelouch","isCover":false,"releaseDate":"Sep 2023","note":""},{"id":"f4b936d1","img":"https://cdn.keycap-archivist.com/keycaps/f4b936d1.jpg","name":"Underworld","isCover":false,"releaseDate":"Oct 2023","note":""},{"id":"3811a01a","img":"https://cdn.keycap-archivist.com/keycaps/3811a01a.jpg","name":"Shinigami","isCover":false,"releaseDate":"Oct 2023","note":""},{"id":"fb903632","img":"https://cdn.keycap-archivist.com/keycaps/fb903632.jpg","name":"Tohru","isCover":false,"releaseDate":"Oct 2023","note":""},{"id":"6c30174a","img":"https://cdn.keycap-archivist.com/keycaps/6c30174a.jpg","name":"Megaira","isCover":false,"releaseDate":"Oct 2023","note":""},{"id":"eefc55da","img":"https://cdn.keycap-archivist.com/keycaps/eefc55da.jpg","name":"Snow Miku","isCover":false,"releaseDate":"Oct 2023","note":""},{"id":"a2ff2747","img":"https://cdn.keycap-archivist.com/keycaps/a2ff2747.jpg","name":"Luffy","isCover":false,"releaseDate":"Oct 2023","note":""},{"id":"e277fe03","img":"https://cdn.keycap-archivist.com/keycaps/e277fe03.jpg","name":"Chika","isCover":false,"releaseDate":"Oct 2023","note":""},{"id":"a4276ee8","img":"https://cdn.keycap-archivist.com/keycaps/a4276ee8.jpg","name":"Espeon","isCover":false,"releaseDate":"Nov 2023","note":""},{"id":"273106d9","img":"https://cdn.keycap-archivist.com/keycaps/273106d9.jpg","name":"Megurine Luka","isCover":false,"releaseDate":"Nov 2023","note":""},{"id":"d8fd9e42","img":"https://cdn.keycap-archivist.com/keycaps/d8fd9e42.jpg","name":"Asuna","isCover":false,"releaseDate":"Nov 2023","note":""},{"id":"c54531e7","img":"https://cdn.keycap-archivist.com/keycaps/c54531e7.jpg","name":"Sylvanas","isCover":false,"releaseDate":"Nov 2023","note":""},{"id":"295b3e51","img":"https://cdn.keycap-archivist.com/keycaps/295b3e51.jpg","name":"Kuroe Shizuku","isCover":false,"releaseDate":"Nov 2023","note":""},{"id":"6df3fd9","img":"https://cdn.keycap-archivist.com/keycaps/6df3fd9.jpg","name":"Dark Paladin","isCover":false,"releaseDate":"Feb 2024","note":""}]},{"id":"33f88d75","name":"Silent Magician","colorways":[{"id":"af40162d","img":"https://cdn.keycap-archivist.com/keycaps/af40162d.jpg","name":"OG","isCover":false,"releaseDate":"Dec 2023","note":""}]},{"id":"f6aff71e","name":"Tourguide","colorways":[{"id":"4d2c0001","img":"https://cdn.keycap-archivist.com/keycaps/4d2c0001.jpg","name":"OG","isCover":false,"releaseDate":"Dec 2023","note":""}]},{"id":"c6ed65c0","name":"Little One","colorways":[{"id":"2bb3863a","img":"https://cdn.keycap-archivist.com/keycaps/2bb3863a.jpg","name":"OG","isCover":false,"releaseDate":"Sep 2022","totalCount":"15","note":""},{"id":"5512942b","img":"https://cdn.keycap-archivist.com/keycaps/5512942b.jpg","name":"Louise","isCover":false,"releaseDate":"Sep 2022","totalCount":"15","note":""},{"id":"2b2c3a8b","img":"https://cdn.keycap-archivist.com/keycaps/2b2c3a8b.jpg","name":"Megumin","isCover":false,"releaseDate":"Sep 2022","totalCount":"15","note":""},{"id":"308c16db","img":"https://cdn.keycap-archivist.com/keycaps/308c16db.jpg","name":"Miku","isCover":false,"releaseDate":"Sep 2022","totalCount":"15","note":""},{"id":"bcb9c58d","img":"https://cdn.keycap-archivist.com/keycaps/bcb9c58d.jpg","name":"Aloy","isCover":false,"releaseDate":"Sep 2022","totalCount":"15","note":""},{"id":"f3583865","img":"https://cdn.keycap-archivist.com/keycaps/f3583865.jpg","name":"10 Billion Percent","isCover":false,"releaseDate":"Sep 2022","totalCount":"25","note":""}]},{"id":"a2495ba5","name":"Tamago","colorways":[{"id":"1416f91f","img":"https://cdn.keycap-archivist.com/keycaps/1416f91f.jpg","name":"Stella","isCover":false,"note":""},{"id":"c21042e9","img":"https://cdn.keycap-archivist.com/keycaps/c21042e9.jpg","name":"Boney","isCover":false,"note":""},{"id":"ef743fb6","img":"https://cdn.keycap-archivist.com/keycaps/ef743fb6.jpg","name":"OG","isCover":false,"note":""},{"id":"b7f4061d","img":"https://cdn.keycap-archivist.com/keycaps/b7f4061d.jpg","name":"Tom","isCover":false,"note":""},{"id":"61f22709","img":"https://cdn.keycap-archivist.com/keycaps/61f22709.jpg","name":"Tiramisu","isCover":false,"note":""},{"id":"137310eb","img":"https://cdn.keycap-archivist.com/keycaps/137310eb.jpg","name":"Soju","isCover":false,"note":""},{"id":"9a49fbb7","img":"https://cdn.keycap-archivist.com/keycaps/9a49fbb7.jpg","name":"Boo","isCover":false,"note":""},{"id":"4ad1e31e","img":"https://cdn.keycap-archivist.com/keycaps/4ad1e31e.jpg","name":"Pumpkin","isCover":false,"note":""},{"id":"abbc7191","img":"https://cdn.keycap-archivist.com/keycaps/abbc7191.jpg","name":"Frosted Heart","isCover":false,"note":""},{"id":"c17b7a8c","img":"https://cdn.keycap-archivist.com/keycaps/c17b7a8c.jpg","name":"Mouthful Phantom","isCover":false,"note":""},{"id":"2a7d25e6","img":"https://cdn.keycap-archivist.com/keycaps/2a7d25e6.jpg","name":"Kuromon","isCover":false,"note":""},{"id":"ac675f56","img":"https://cdn.keycap-archivist.com/keycaps/ac675f56.jpg","name":"Shiromon","isCover":false,"note":""},{"id":"3a7c267","img":"https://cdn.keycap-archivist.com/keycaps/3a7c267.jpg","name":"Chaos Nir","isCover":false,"note":""},{"id":"19a425be","img":"https://cdn.keycap-archivist.com/keycaps/19a425be.jpg","name":"Megumin","isCover":false,"note":""},{"id":"ffc6f548","img":"https://cdn.keycap-archivist.com/keycaps/ffc6f548.jpg","name":"Batago","isCover":false,"note":""},{"id":"5f83e87a","img":"https://cdn.keycap-archivist.com/keycaps/5f83e87a.jpg","name":"Intersteller","isCover":false,"note":""},{"id":"fa7cb827","img":"https://cdn.keycap-archivist.com/keycaps/fa7cb827.jpg","name":"Christmas","isCover":false,"note":""},{"id":"c66b34b5","img":"https://cdn.keycap-archivist.com/keycaps/c66b34b5.jpg","name":"That's A Wrap","isCover":false,"totalCount":"1","note":""},{"id":"8296b230","img":"https://cdn.keycap-archivist.com/keycaps/8296b230.jpg","name":"Itachi","isCover":false,"note":""},{"id":"b64a59bc","img":"https://cdn.keycap-archivist.com/keycaps/b64a59bc.jpg","name":"Sasuke","isCover":false,"note":""},{"id":"1856476e","img":"https://cdn.keycap-archivist.com/keycaps/1856476e.jpg","name":"Meowlonkeys","isCover":false,"totalCount":"1","note":""},{"id":"3f2104e1","img":"https://cdn.keycap-archivist.com/keycaps/3f2104e1.jpg","name":"Arsonist","isCover":false,"note":""},{"id":"6f6f8f28","img":"https://cdn.keycap-archivist.com/keycaps/6f6f8f28.jpg","name":"Voyager","isCover":false,"note":""},{"id":"cf7af81f","img":"https://cdn.keycap-archivist.com/keycaps/cf7af81f.jpg","name":"Luminescence","isCover":false,"totalCount":"1","note":""},{"id":"c86199e4","img":"https://cdn.keycap-archivist.com/keycaps/c86199e4.jpg","name":"Miku","isCover":false,"note":""},{"id":"8de52fa0","img":"https://cdn.keycap-archivist.com/keycaps/8de52fa0.jpg","name":"Sogurt","isCover":false,"note":""},{"id":"3752d9c","img":"https://cdn.keycap-archivist.com/keycaps/3752d9c.jpg","name":"MHA Todoroki","isCover":false,"note":""},{"id":"7f5595d3","img":"https://cdn.keycap-archivist.com/keycaps/7f5595d3.jpg","name":"Deku","isCover":false,"note":""},{"id":"dc299480","img":"https://cdn.keycap-archivist.com/keycaps/dc299480.jpg","name":"EVA-01","isCover":false,"note":""},{"id":"d6df2687","img":"https://cdn.keycap-archivist.com/keycaps/d6df2687.jpg","name":"Nostalgia","isCover":false,"note":""},{"id":"1575b900","img":"https://cdn.keycap-archivist.com/keycaps/1575b900.jpg","name":"Beacon","isCover":false,"note":""},{"id":"17e1eecf","img":"https://cdn.keycap-archivist.com/keycaps/17e1eecf.jpg","name":"Lusty","isCover":false,"note":""},{"id":"2d8eb818","img":"https://cdn.keycap-archivist.com/keycaps/2d8eb818.jpg","name":"Mariner9","isCover":false,"note":""},{"id":"d3e7cb04","img":"https://cdn.keycap-archivist.com/keycaps/d3e7cb04.jpg","name":"Virgo","isCover":false,"note":""},{"id":"4f08f144","img":"https://cdn.keycap-archivist.com/keycaps/4f08f144.jpg","name":"Doraemon","isCover":false,"note":""},{"id":"9ca7c70d","img":"https://cdn.keycap-archivist.com/keycaps/9ca7c70d.jpg","name":"Chopper","isCover":false,"note":""},{"id":"3b7ad852","img":"https://cdn.keycap-archivist.com/keycaps/3b7ad852.jpg","name":"Joker","isCover":false,"note":""},{"id":"a9a3559c","img":"https://cdn.keycap-archivist.com/keycaps/a9a3559c.jpg","name":"Harley","isCover":false,"note":""}]},{"id":"c97a81c4","name":"Suika v2","colorways":[{"id":"ab84ca50","img":"https://cdn.keycap-archivist.com/keycaps/ab84ca50.jpg","name":"Sasuke","isCover":false,"note":""},{"id":"e7c86d3e","img":"https://cdn.keycap-archivist.com/keycaps/e7c86d3e.jpg","name":"Encore","isCover":false,"note":""},{"id":"55dbcea3","img":"https://cdn.keycap-archivist.com/keycaps/55dbcea3.jpg","name":"Carbon","isCover":false,"note":""},{"id":"59a7e8a0","img":"https://cdn.keycap-archivist.com/keycaps/59a7e8a0.jpg","name":"Stargaze","isCover":false,"note":""},{"id":"112393e5","img":"https://cdn.keycap-archivist.com/keycaps/112393e5.jpg","name":"No Face","isCover":false,"note":""},{"id":"de8b63f6","img":"https://cdn.keycap-archivist.com/keycaps/de8b63f6.jpg","name":"Pharaoh","isCover":false,"note":""},{"id":"95fe747","img":"https://cdn.keycap-archivist.com/keycaps/95fe747.jpg","name":"a","isCover":false,"note":""}]},{"id":"ef219b5c","name":"Sumo v2","colorways":[{"id":"b7692e01","img":"https://cdn.keycap-archivist.com/keycaps/b7692e01.jpg","name":"Uchiha","isCover":false,"note":""},{"id":"dbf2cf64","img":"https://cdn.keycap-archivist.com/keycaps/dbf2cf64.jpg","name":"Encore","isCover":false,"note":""},{"id":"eacbc5b0","img":"https://cdn.keycap-archivist.com/keycaps/eacbc5b0.jpg","name":"Carbon","isCover":false,"note":""},{"id":"3727a424","img":"https://cdn.keycap-archivist.com/keycaps/3727a424.jpg","name":"Stargaze","isCover":false,"note":""},{"id":"fd20601e","img":"https://cdn.keycap-archivist.com/keycaps/fd20601e.jpg","name":"No Face","isCover":false,"note":""},{"id":"4cca9655","img":"https://cdn.keycap-archivist.com/keycaps/4cca9655.jpg","name":"Pharaoh","isCover":false,"note":""},{"id":"e22f93f1","img":"https://cdn.keycap-archivist.com/keycaps/e22f93f1.jpg","name":"a","isCover":false,"note":""}]},{"id":"d7d7eeba","name":"Dark Magician","colorways":[{"id":"bd4e58ed","img":"https://cdn.keycap-archivist.com/keycaps/bd4e58ed.jpg","name":"Original","isCover":false,"note":""},{"id":"38539874","img":"https://cdn.keycap-archivist.com/keycaps/38539874.jpg","name":"Ancient Curse","isCover":false,"note":""},{"id":"8b072b3c","img":"https://cdn.keycap-archivist.com/keycaps/8b072b3c.jpg","name":"Blue Eyes","isCover":false,"note":""},{"id":"258a17dc","img":"https://cdn.keycap-archivist.com/keycaps/258a17dc.jpg","name":"MoMo","isCover":false,"note":""},{"id":"3dfcc46a","img":"https://cdn.keycap-archivist.com/keycaps/3dfcc46a.jpg","name":"Taro","isCover":false,"note":""},{"id":"4a1e241b","img":"https://cdn.keycap-archivist.com/keycaps/4a1e241b.jpg","name":"No Face","isCover":false,"note":""},{"id":"b6285999","img":"https://cdn.keycap-archivist.com/keycaps/b6285999.jpg","name":"Itachi","isCover":false,"note":""},{"id":"f3ea5778","img":"https://cdn.keycap-archivist.com/keycaps/f3ea5778.jpg","name":"Megumin","isCover":false,"note":""},{"id":"e54b1be7","img":"https://cdn.keycap-archivist.com/keycaps/e54b1be7.jpg","name":"Ramses","isCover":false,"note":""},{"id":"162a00e","img":"https://cdn.keycap-archivist.com/keycaps/162a00e.jpg","name":"Daifuku","isCover":false,"note":""},{"id":"8d821c1f","img":"https://cdn.keycap-archivist.com/keycaps/8d821c1f.jpg","name":"Harvest","isCover":false,"note":""},{"id":"63f78dd1","img":"https://cdn.keycap-archivist.com/keycaps/63f78dd1.jpg","name":"a","isCover":false,"note":""},{"id":"d3683e4d","img":"https://cdn.keycap-archivist.com/keycaps/d3683e4d.jpg","name":"Trüffelschwein","isCover":false,"note":""},{"id":"d480a922","img":"https://cdn.keycap-archivist.com/keycaps/d480a922.jpg","name":"Tiramisu","isCover":false,"note":""},{"id":"bb469f16","img":"https://cdn.keycap-archivist.com/keycaps/bb469f16.jpg","name":"Kurious","isCover":false,"note":""},{"id":"7259119c","img":"https://cdn.keycap-archivist.com/keycaps/7259119c.jpg","name":"Tako","isCover":false,"note":""},{"id":"f43c665e","img":"https://cdn.keycap-archivist.com/keycaps/f43c665e.jpg","name":"Coloradas","isCover":false,"note":""},{"id":"87724980","img":"https://cdn.keycap-archivist.com/keycaps/87724980.jpg","name":"Phantom","isCover":false,"note":""},{"id":"d2c9f54f","img":"https://cdn.keycap-archivist.com/keycaps/d2c9f54f.jpg","name":"Frosted Heart","isCover":false,"note":""},{"id":"2dfc3a8b","img":"https://cdn.keycap-archivist.com/keycaps/2dfc3a8b.jpg","name":"Chaos Nir","isCover":false,"note":""},{"id":"667540b5","img":"https://cdn.keycap-archivist.com/keycaps/667540b5.jpg","name":"MHA Todoroki","isCover":false,"note":""},{"id":"5ae2cc6b","img":"https://cdn.keycap-archivist.com/keycaps/5ae2cc6b.jpg","name":"EVA-01","isCover":false,"note":""},{"id":"6b79fe57","img":"https://cdn.keycap-archivist.com/keycaps/6b79fe57.jpg","name":"Christmas","isCover":false,"note":""},{"id":"15f095f0","img":"https://cdn.keycap-archivist.com/keycaps/15f095f0.jpg","name":"That's A Wrap","isCover":false,"totalCount":"1","note":""},{"id":"5e79ad5d","img":"https://cdn.keycap-archivist.com/keycaps/5e79ad5d.jpg","name":"Deku","isCover":false,"note":""},{"id":"f1a22b61","img":"https://cdn.keycap-archivist.com/keycaps/f1a22b61.jpg","name":"Voyager","isCover":false,"note":""},{"id":"9f380cb3","img":"https://cdn.keycap-archivist.com/keycaps/9f380cb3.jpg","name":"Arsonist","isCover":false,"note":""},{"id":"4e8e280","img":"https://cdn.keycap-archivist.com/keycaps/4e8e280.jpg","name":"Luminescence","isCover":false,"totalCount":"1","note":""},{"id":"ad8e17b5","img":"https://cdn.keycap-archivist.com/keycaps/ad8e17b5.jpg","name":"Miku","isCover":false,"note":""},{"id":"8f5bbb6f","img":"https://cdn.keycap-archivist.com/keycaps/8f5bbb6f.jpg","name":"Sogurt","isCover":false,"note":""},{"id":"9e82b739","img":"https://cdn.keycap-archivist.com/keycaps/9e82b739.jpg","name":"Nostalgia","isCover":false,"note":""},{"id":"478a2116","img":"https://cdn.keycap-archivist.com/keycaps/478a2116.jpg","name":"Lusty","isCover":false,"note":""},{"id":"ed2e0b16","img":"https://cdn.keycap-archivist.com/keycaps/ed2e0b16.jpg","name":"Mariner9","isCover":false,"note":""},{"id":"8ed2ecf9","img":"https://cdn.keycap-archivist.com/keycaps/8ed2ecf9.jpg","name":"Dragon Knight","isCover":false,"note":""},{"id":"19e5628e","img":"https://cdn.keycap-archivist.com/keycaps/19e5628e.jpg","name":"Harley","isCover":false,"note":""},{"id":"801c12a9","img":"https://cdn.keycap-archivist.com/keycaps/801c12a9.jpg","name":"Joker","isCover":false,"note":""},{"id":"6fde00ed","img":"https://cdn.keycap-archivist.com/keycaps/6fde00ed.jpg","name":"Emerald","isCover":false,"totalCount":"1","note":""},{"id":"3d3e12c9","img":"https://cdn.keycap-archivist.com/keycaps/3d3e12c9.jpg","name":"Dracula","isCover":false,"releaseDate":"Nov 2023","note":""},{"id":"ff92e637","img":"https://cdn.keycap-archivist.com/keycaps/ff92e637.jpg","name":"Vegeta","isCover":false,"releaseDate":"Nov 2023","note":""},{"id":"5c6bc516","img":"https://cdn.keycap-archivist.com/keycaps/5c6bc516.jpg","name":"Sesshomaru","isCover":false,"releaseDate":"Nov 2023","note":""},{"id":"9f98adc6","img":"https://cdn.keycap-archivist.com/keycaps/9f98adc6.jpg","name":"Shiro","isCover":false,"releaseDate":"Dec 2023","note":""},{"id":"d5fb7219","img":"https://cdn.keycap-archivist.com/keycaps/d5fb7219.jpg","name":"Zoro","isCover":false,"releaseDate":"Dec 2023","note":""},{"id":"5a612126","img":"https://cdn.keycap-archivist.com/keycaps/5a612126.jpg","name":"Links","isCover":false,"releaseDate":"Dec 2023","note":""},{"id":"b0f16414","img":"https://cdn.keycap-archivist.com/keycaps/b0f16414.jpg","name":"Stardust","isCover":false,"releaseDate":"Dec 2023","note":""},{"id":"aebaa588","img":"https://cdn.keycap-archivist.com/keycaps/aebaa588.jpg","name":"BlackJack","isCover":false,"releaseDate":"jan 2024","note":""},{"id":"1dcce224","img":"https://cdn.keycap-archivist.com/keycaps/1dcce224.jpg","name":"Sketch","isCover":false,"releaseDate":"Jan 2024","note":""},{"id":"eea499f7","img":"https://cdn.keycap-archivist.com/keycaps/eea499f7.jpg","name":"Ishtar","isCover":false,"releaseDate":"Jan 2024","note":""},{"id":"12acfe2c","img":"https://cdn.keycap-archivist.com/keycaps/12acfe2c.jpg","name":"Milky","isCover":false,"releaseDate":"Feb 2024","note":""}]},{"id":"354328e6","name":"Dark Magician Girl","colorways":[{"id":"49f6a1c4","img":"https://cdn.keycap-archivist.com/keycaps/49f6a1c4.jpg","name":"Original","isCover":false,"note":""},{"id":"fae85f90","img":"https://cdn.keycap-archivist.com/keycaps/fae85f90.jpg","name":"Jubilant OG","isCover":false,"totalCount":"1","giveaway":true,"note":""},{"id":"b011bbb2","img":"https://cdn.keycap-archivist.com/keycaps/b011bbb2.jpg","name":"Ancient Curse","isCover":false,"note":""},{"id":"1dc8c831","img":"https://cdn.keycap-archivist.com/keycaps/1dc8c831.jpg","name":"Blue Eyes","isCover":false,"note":""},{"id":"3d296726","img":"https://cdn.keycap-archivist.com/keycaps/3d296726.jpg","name":"MoMo","isCover":false,"note":""},{"id":"c132d306","img":"https://cdn.keycap-archivist.com/keycaps/c132d306.jpg","name":"Taro","isCover":false,"note":""},{"id":"8fb845a4","img":"https://cdn.keycap-archivist.com/keycaps/8fb845a4.jpg","name":"No Face","isCover":false,"note":""},{"id":"d00c38d4","img":"https://cdn.keycap-archivist.com/keycaps/d00c38d4.jpg","name":"Totoro","isCover":false,"note":""},{"id":"da850643","img":"https://cdn.keycap-archivist.com/keycaps/da850643.jpg","name":"Darth Vader","isCover":false,"note":""},{"id":"88d97836","img":"https://cdn.keycap-archivist.com/keycaps/88d97836.jpg","name":"Kumamon","isCover":false,"note":""},{"id":"8239ba50","img":"https://cdn.keycap-archivist.com/keycaps/8239ba50.jpg","name":"Pikachu","isCover":false,"note":""},{"id":"3f589c6c","img":"https://cdn.keycap-archivist.com/keycaps/3f589c6c.jpg","name":"Mono","isCover":false,"note":""},{"id":"84b01f6e","img":"https://cdn.keycap-archivist.com/keycaps/84b01f6e.jpg","name":"Sasuke","isCover":false,"note":""},{"id":"79f0590c","img":"https://cdn.keycap-archivist.com/keycaps/79f0590c.jpg","name":"Daruma","isCover":false,"note":""},{"id":"7e26af7f","img":"https://cdn.keycap-archivist.com/keycaps/7e26af7f.jpg","name":"Paranoise","isCover":false,"note":""},{"id":"1631482e","img":"https://cdn.keycap-archivist.com/keycaps/1631482e.jpg","name":"Chameleon","isCover":false,"note":""},{"id":"6e54ad52","img":"https://cdn.keycap-archivist.com/keycaps/6e54ad52.jpg","name":"Jigsaw","isCover":false,"note":""},{"id":"84ab03c1","img":"https://cdn.keycap-archivist.com/keycaps/84ab03c1.jpg","name":"Doraemon","isCover":false,"note":""},{"id":"561c5dd6","img":"https://cdn.keycap-archivist.com/keycaps/561c5dd6.jpg","name":"Nezuko","isCover":false,"note":""},{"id":"ea7e36a","img":"https://cdn.keycap-archivist.com/keycaps/ea7e36a.jpg","name":"Pandora","isCover":false,"note":""},{"id":"d4da3e5e","img":"https://cdn.keycap-archivist.com/keycaps/d4da3e5e.jpg","name":"Ironkitty","isCover":false,"note":""},{"id":"61a2962b","img":"https://cdn.keycap-archivist.com/keycaps/61a2962b.jpg","name":"Seeingthings","isCover":false,"note":""},{"id":"d225ce69","img":"https://cdn.keycap-archivist.com/keycaps/d225ce69.jpg","name":"Ironlady","isCover":false,"note":""},{"id":"1a0f0202","img":"https://cdn.keycap-archivist.com/keycaps/1a0f0202.jpg","name":"Gamma Radiation","isCover":false,"note":""},{"id":"650a0cb2","img":"https://cdn.keycap-archivist.com/keycaps/650a0cb2.jpg","name":"Megumin","isCover":false,"note":""},{"id":"768bbdaa","img":"https://cdn.keycap-archivist.com/keycaps/768bbdaa.jpg","name":"Ramses","isCover":false,"note":""},{"id":"76c93575","img":"https://cdn.keycap-archivist.com/keycaps/76c93575.jpg","name":"Mad Titan","isCover":false,"note":""},{"id":"f1faa89d","img":"https://cdn.keycap-archivist.com/keycaps/f1faa89d.jpg","name":"Daifuku","isCover":false,"note":""},{"id":"903a9704","img":"https://cdn.keycap-archivist.com/keycaps/903a9704.jpg","name":"Buu","isCover":false,"note":""},{"id":"8916beb1","img":"https://cdn.keycap-archivist.com/keycaps/8916beb1.jpg","name":"Harvest","isCover":false,"note":""},{"id":"2a2d2b18","img":"https://cdn.keycap-archivist.com/keycaps/2a2d2b18.jpg","name":"a","isCover":false,"note":""},{"id":"f0a78569","img":"https://cdn.keycap-archivist.com/keycaps/f0a78569.jpg","name":"Trüffelschwein","isCover":false,"note":""},{"id":"4d613c7f","img":"https://cdn.keycap-archivist.com/keycaps/4d613c7f.jpg","name":"Tiramisu","isCover":false,"note":""},{"id":"958940b","img":"https://cdn.keycap-archivist.com/keycaps/958940b.jpg","name":"Kurious","isCover":false,"note":""},{"id":"58190f44","img":"https://cdn.keycap-archivist.com/keycaps/58190f44.jpg","name":"Tako","isCover":false,"note":""},{"id":"30701e3b","img":"https://cdn.keycap-archivist.com/keycaps/30701e3b.jpg","name":"Coloradas","isCover":false,"note":""},{"id":"7927f374","img":"https://cdn.keycap-archivist.com/keycaps/7927f374.jpg","name":"Phantom","isCover":false,"note":""},{"id":"40006490","img":"https://cdn.keycap-archivist.com/keycaps/40006490.jpg","name":"Frosted Heart","isCover":false,"note":""},{"id":"54ea81b4","img":"https://cdn.keycap-archivist.com/keycaps/54ea81b4.jpg","name":"Chaos Nir","isCover":false,"note":""},{"id":"4339d4ff","img":"https://cdn.keycap-archivist.com/keycaps/4339d4ff.jpg","name":"MHA Todoroki","isCover":false,"note":""},{"id":"b47e30c2","img":"https://cdn.keycap-archivist.com/keycaps/b47e30c2.jpg","name":"EVA-01","isCover":false,"note":""},{"id":"ca6f6988","img":"https://cdn.keycap-archivist.com/keycaps/ca6f6988.jpg","name":"Christmas","isCover":false,"note":""},{"id":"83bbcee4","img":"https://cdn.keycap-archivist.com/keycaps/83bbcee4.jpg","name":"That's A Wrap","isCover":false,"totalCount":"1","note":""},{"id":"503c4bce","img":"https://cdn.keycap-archivist.com/keycaps/503c4bce.jpg","name":"Deku","isCover":false,"note":""},{"id":"f1190046","img":"https://cdn.keycap-archivist.com/keycaps/f1190046.jpg","name":"Voyager","isCover":false,"note":""},{"id":"dd10125f","img":"https://cdn.keycap-archivist.com/keycaps/dd10125f.jpg","name":"Arsonist","isCover":false,"note":""},{"id":"3cd29d79","img":"https://cdn.keycap-archivist.com/keycaps/3cd29d79.jpg","name":"Luminescence","isCover":false,"totalCount":"1","note":""},{"id":"b07e86c1","img":"https://cdn.keycap-archivist.com/keycaps/b07e86c1.jpg","name":"Miku","isCover":false,"note":""},{"id":"5b24b325","img":"https://cdn.keycap-archivist.com/keycaps/5b24b325.jpg","name":"Sogurt","isCover":false,"note":""},{"id":"d63df8c2","img":"https://cdn.keycap-archivist.com/keycaps/d63df8c2.jpg","name":"Nostalgia","isCover":false,"note":""},{"id":"26bd8f33","img":"https://cdn.keycap-archivist.com/keycaps/26bd8f33.jpg","name":"Lusty","isCover":false,"note":""},{"id":"a4efd82b","img":"https://cdn.keycap-archivist.com/keycaps/a4efd82b.jpg","name":"Mariner9","isCover":false,"note":""},{"id":"b9e65c63","img":"https://cdn.keycap-archivist.com/keycaps/b9e65c63.jpg","name":"Dragon Knight","isCover":false,"note":""},{"id":"31fcb659","img":"https://cdn.keycap-archivist.com/keycaps/31fcb659.jpg","name":"Harley","isCover":false,"note":""},{"id":"bebc304a","img":"https://cdn.keycap-archivist.com/keycaps/bebc304a.jpg","name":"Joker","isCover":false,"note":""},{"id":"3d5fbf7","img":"https://cdn.keycap-archivist.com/keycaps/3d5fbf7.jpg","name":"Gawr Gura","isCover":false,"releaseDate":"Mar 2023","note":""},{"id":"280536ec","img":"https://cdn.keycap-archivist.com/keycaps/280536ec.jpg","name":"OG Reversed","isCover":false,"releaseDate":"Mar 2023","note":""},{"id":"a8b0ee34","img":"https://cdn.keycap-archivist.com/keycaps/a8b0ee34.jpg","name":"Euler","isCover":false,"releaseDate":"Apr 2023","note":""},{"id":"f7688413","img":"https://cdn.keycap-archivist.com/keycaps/f7688413.jpg","name":"Dark Melon","isCover":false,"releaseDate":"Apr 2023","note":""},{"id":"5ea88775","img":"https://cdn.keycap-archivist.com/keycaps/5ea88775.jpg","name":"Hogwarts Legends: Godric","isCover":false,"releaseDate":"Apr 2023","note":""},{"id":"599b1cfc","img":"https://cdn.keycap-archivist.com/keycaps/599b1cfc.jpg","name":"Hogwarts Legends: Salazar","isCover":false,"releaseDate":"Apr 2023","note":""},{"id":"d9f5dbe1","img":"https://cdn.keycap-archivist.com/keycaps/d9f5dbe1.jpg","name":"Team Rocket: Jessie","isCover":false,"releaseDate":"Apr 2023","note":""},{"id":"219b3317","img":"https://cdn.keycap-archivist.com/keycaps/219b3317.jpg","name":"Kaiju","isCover":false,"releaseDate":"Apr 2023","note":""},{"id":"3a6038be","img":"https://cdn.keycap-archivist.com/keycaps/3a6038be.jpg","name":"Copper","isCover":false,"releaseDate":"May 2023","note":""},{"id":"cbbb4cb8","img":"https://cdn.keycap-archivist.com/keycaps/cbbb4cb8.jpg","name":"Nanaba","isCover":false,"releaseDate":"May 2023","note":""},{"id":"ee587a09","img":"https://cdn.keycap-archivist.com/keycaps/ee587a09.jpg","name":"Yun","isCover":false,"releaseDate":"Jun 2023","note":""},{"id":"33a0596c","img":"https://cdn.keycap-archivist.com/keycaps/33a0596c.jpg","name":"Xing","isCover":false,"releaseDate":"Jun 2023","note":""},{"id":"b074b9","img":"https://cdn.keycap-archivist.com/keycaps/b074b9.jpg","name":"Tatsumaki","isCover":false,"releaseDate":"Jun 2023","note":""},{"id":"1a7d1e2c","img":"https://cdn.keycap-archivist.com/keycaps/1a7d1e2c.jpg","name":"Abandoned","isCover":false,"releaseDate":"Jun 2023","totalCount":"1","note":""},{"id":"bb084877","img":"https://cdn.keycap-archivist.com/keycaps/bb084877.jpg","name":"Mictlán","isCover":false,"releaseDate":"Jun 2023","note":""},{"id":"b72e7746","img":"https://cdn.keycap-archivist.com/keycaps/b72e7746.jpg","name":"Darling","isCover":false,"releaseDate":"Jun 2023","note":""},{"id":"ca3f04b7","img":"https://cdn.keycap-archivist.com/keycaps/ca3f04b7.jpg","name":"Roxy","isCover":false,"releaseDate":"Jun 2023","note":""},{"id":"b5e96dfb","img":"https://cdn.keycap-archivist.com/keycaps/b5e96dfb.jpg","name":"Hazakura","isCover":false,"releaseDate":"July 2023","note":""},{"id":"2d11f437","img":"https://cdn.keycap-archivist.com/keycaps/2d11f437.jpg","name":"Buzz","isCover":false,"releaseDate":"July 2023","note":""},{"id":"478d8676","img":"https://cdn.keycap-archivist.com/keycaps/478d8676.jpg","name":"Summer","isCover":false,"releaseDate":"July 2023","note":""},{"id":"1dbaf684","img":"https://cdn.keycap-archivist.com/keycaps/1dbaf684.jpg","name":"Necross","isCover":false,"releaseDate":"July 2023","note":""},{"id":"1ff2620d","img":"https://cdn.keycap-archivist.com/keycaps/1ff2620d.jpg","name":"Kikyo","isCover":false,"releaseDate":"July 2023","note":""},{"id":"f32c7a65","img":"https://cdn.keycap-archivist.com/keycaps/f32c7a65.jpg","name":"D.VA","isCover":false,"releaseDate":"Aug 2023","note":""},{"id":"503338b9","img":"https://cdn.keycap-archivist.com/keycaps/503338b9.jpg","name":"EVA-02","isCover":false,"releaseDate":"Aug 2023","note":""},{"id":"d50043f3","img":"https://cdn.keycap-archivist.com/keycaps/d50043f3.jpg","name":"Saber","isCover":false,"releaseDate":"Aug 2023","note":""},{"id":"2596cd8e","img":"https://cdn.keycap-archivist.com/keycaps/2596cd8e.jpg","name":"Saber Alter","isCover":false,"releaseDate":"Aug 2023","note":""},{"id":"99add238","img":"https://cdn.keycap-archivist.com/keycaps/99add238.jpg","name":"Kill la Kill","isCover":false,"releaseDate":"Sep 2023","note":""},{"id":"cc0978af","img":"https://cdn.keycap-archivist.com/keycaps/cc0978af.jpg","name":"Nahida","isCover":false,"releaseDate":"Sep 2023","note":""},{"id":"2d5a0e13","img":"https://cdn.keycap-archivist.com/keycaps/2d5a0e13.jpg","name":"Nier","isCover":false,"releaseDate":"Sep 2023","note":""},{"id":"89af8033","img":"https://cdn.keycap-archivist.com/keycaps/89af8033.jpg","name":"C.C","isCover":false,"releaseDate":"Sep 2023","note":""},{"id":"49329642","img":"https://cdn.keycap-archivist.com/keycaps/49329642.jpg","name":"Ursula","isCover":false,"releaseDate":"Sep 2023","note":""},{"id":"1cba33b","img":"https://cdn.keycap-archivist.com/keycaps/1cba33b.jpg","name":"Underworld","isCover":false,"releaseDate":"Oct 2023","note":""},{"id":"8fa772f0","img":"https://cdn.keycap-archivist.com/keycaps/8fa772f0.jpg","name":"Shinigami","isCover":false,"releaseDate":"Oct 2023","note":""},{"id":"4aaf7870","img":"https://cdn.keycap-archivist.com/keycaps/4aaf7870.jpg","name":"Tohru","isCover":false,"releaseDate":"Oct 2023","note":""},{"id":"ec7675a8","img":"https://cdn.keycap-archivist.com/keycaps/ec7675a8.jpg","name":"Megaira","isCover":false,"releaseDate":"Oct 2023","note":""},{"id":"b6524d5","img":"https://cdn.keycap-archivist.com/keycaps/b6524d5.jpg","name":"Snow Miku","isCover":false,"releaseDate":"Oct 2023","note":""},{"id":"f4cd6bf2","img":"https://cdn.keycap-archivist.com/keycaps/f4cd6bf2.jpg","name":"Luffy","isCover":false,"releaseDate":"Oct 2023","note":""},{"id":"55389420","img":"https://cdn.keycap-archivist.com/keycaps/55389420.jpg","name":"Chika","isCover":false,"releaseDate":"Oct 2023","note":""},{"id":"117ee914","img":"https://cdn.keycap-archivist.com/keycaps/117ee914.jpg","name":"Umbreon","isCover":false,"releaseDate":"Nov 2023","note":""},{"id":"3684ab33","img":"https://cdn.keycap-archivist.com/keycaps/3684ab33.jpg","name":"Megurine Luka","isCover":false,"releaseDate":"Nov 2023","note":""},{"id":"87264443","img":"https://cdn.keycap-archivist.com/keycaps/87264443.jpg","name":"Dracula","isCover":false,"releaseDate":"Nov 2023","note":""},{"id":"a59d6680","img":"https://cdn.keycap-archivist.com/keycaps/a59d6680.jpg","name":"Bulma","isCover":false,"releaseDate":"Nov 2023","note":""},{"id":"ff66cf3d","img":"https://cdn.keycap-archivist.com/keycaps/ff66cf3d.jpg","name":"Sesshomaru","isCover":false,"releaseDate":"Nov 2023","note":""},{"id":"aa5d3add","img":"https://cdn.keycap-archivist.com/keycaps/aa5d3add.jpg","name":"Asuna","isCover":false,"releaseDate":"Nov 2023","note":""},{"id":"6320affd","img":"https://cdn.keycap-archivist.com/keycaps/6320affd.jpg","name":"Sylvanas","isCover":false,"releaseDate":"Nov 2023","note":""},{"id":"d0d2509c","img":"https://cdn.keycap-archivist.com/keycaps/d0d2509c.jpg","name":"Kuroe Shizuku","isCover":false,"releaseDate":"Nov 2023","note":""},{"id":"428304ca","img":"https://cdn.keycap-archivist.com/keycaps/428304ca.jpg","name":"Shiro","isCover":false,"releaseDate":"Dec 2023","note":""},{"id":"4dbb0202","img":"https://cdn.keycap-archivist.com/keycaps/4dbb0202.jpg","name":"Nami","isCover":false,"releaseDate":"Dec 2023","note":""},{"id":"16acfe50","img":"https://cdn.keycap-archivist.com/keycaps/16acfe50.jpg","name":"Zelda","isCover":false,"releaseDate":"Dec 2023","note":""},{"id":"4ac820ca","img":"https://cdn.keycap-archivist.com/keycaps/4ac820ca.jpg","name":"Obito","isCover":false,"releaseDate":"Dec 2023","note":""},{"id":"f115fc5","img":"https://cdn.keycap-archivist.com/keycaps/f115fc5.jpg","name":"Stardust","isCover":false,"releaseDate":"Dec 2023","note":""},{"id":"dd61d371","img":"https://cdn.keycap-archivist.com/keycaps/dd61d371.jpg","name":"Jack Skellington","isCover":false,"releaseDate":"Dec 2023","note":""},{"id":"aba791a7","img":"https://cdn.keycap-archivist.com/keycaps/aba791a7.jpg","name":"Xmas","isCover":false,"releaseDate":"Dec 2023","note":""},{"id":"4155a1e8","img":"https://cdn.keycap-archivist.com/keycaps/4155a1e8.jpg","name":"Chloe - Mask on","isCover":false,"releaseDate":"Jan 2024","note":""},{"id":"18cfdd44","img":"https://cdn.keycap-archivist.com/keycaps/18cfdd44.jpg","name":"Chloe","isCover":false,"releaseDate":"Jan 2024","note":""},{"id":"85d9026d","img":"https://cdn.keycap-archivist.com/keycaps/85d9026d.jpg","name":"BlackJack","isCover":false,"releaseDate":"Jan 2024","note":""},{"id":"2474829e","img":"https://cdn.keycap-archivist.com/keycaps/2474829e.jpg","name":"Sketch","isCover":false,"releaseDate":"Jan 2024","note":""},{"id":"a4ca839f","img":"https://cdn.keycap-archivist.com/keycaps/a4ca839f.jpg","name":"Gojo","isCover":false,"releaseDate":"Jan 2024","note":""},{"id":"246d54dc","img":"https://cdn.keycap-archivist.com/keycaps/246d54dc.jpg","name":"Ishtar","isCover":false,"releaseDate":"Jan 2024","note":""},{"id":"eca2fb1b","img":"https://cdn.keycap-archivist.com/keycaps/eca2fb1b.jpg","name":"Nezuko","isCover":false,"releaseDate":"Jan 2024","note":""},{"id":"1fc7e962","img":"https://cdn.keycap-archivist.com/keycaps/1fc7e962.jpg","name":"Dark Paladin","isCover":false,"releaseDate":"Feb 2024","note":""},{"id":"4b8f91b8","img":"https://cdn.keycap-archivist.com/keycaps/4b8f91b8.jpg","name":"Milky","isCover":false,"releaseDate":"Feb 2024","note":""}]},{"id":"53bb8e39","name":"Kamikaze","colorways":[{"id":"dae9e1e4","img":"https://cdn.keycap-archivist.com/keycaps/dae9e1e4.jpg","name":"8008","isCover":false,"note":""},{"id":"699bc556","img":"https://cdn.keycap-archivist.com/keycaps/699bc556.jpg","name":"Black Pink","isCover":false,"note":""},{"id":"42e08867","img":"https://cdn.keycap-archivist.com/keycaps/42e08867.jpg","name":"Camping","isCover":false,"note":""},{"id":"432d5d0d","img":"https://cdn.keycap-archivist.com/keycaps/432d5d0d.jpg","name":"Carbon","isCover":false,"note":""},{"id":"f682687d","img":"https://cdn.keycap-archivist.com/keycaps/f682687d.jpg","name":"Death Beam","isCover":false,"note":""},{"id":"a905b836","img":"https://cdn.keycap-archivist.com/keycaps/a905b836.jpg","name":"Hogwarts Assemble - Gryffindor","isCover":false,"note":""},{"id":"21aec349","img":"https://cdn.keycap-archivist.com/keycaps/21aec349.jpg","name":"Hogwarts Assemble - Hufflepuff","isCover":false,"note":""},{"id":"8909a49a","img":"https://cdn.keycap-archivist.com/keycaps/8909a49a.jpg","name":"Hogwarts Assemble - Slytherin","isCover":false,"note":""},{"id":"e0f2a700","img":"https://cdn.keycap-archivist.com/keycaps/e0f2a700.jpg","name":"Hogwarts Assemble - Ravenclaw","isCover":false,"note":""},{"id":"71b49fab","img":"https://cdn.keycap-archivist.com/keycaps/71b49fab.jpg","name":"KAT Iron","isCover":false,"note":""},{"id":"13b0e4be","img":"https://cdn.keycap-archivist.com/keycaps/13b0e4be.jpg","name":"Metro","isCover":false,"note":""},{"id":"f3906243","img":"https://cdn.keycap-archivist.com/keycaps/f3906243.jpg","name":"Olympus - Hades","isCover":false,"note":""},{"id":"d7dca50f","img":"https://cdn.keycap-archivist.com/keycaps/d7dca50f.jpg","name":"Olympus - Poseidon","isCover":false,"note":""},{"id":"9bd94665","img":"https://cdn.keycap-archivist.com/keycaps/9bd94665.jpg","name":"Olympus - Zeus","isCover":false,"note":""},{"id":"3a9e3c53","img":"https://cdn.keycap-archivist.com/keycaps/3a9e3c53.jpg","name":"Taro","isCover":false,"note":""},{"id":"f958dae0","img":"https://cdn.keycap-archivist.com/keycaps/f958dae0.jpg","name":"Blue Trooper","isCover":false,"note":""},{"id":"ad4a5704","img":"https://cdn.keycap-archivist.com/keycaps/ad4a5704.jpg","name":"Valorant Pink","isCover":false,"note":""},{"id":"7e0a834c","img":"https://cdn.keycap-archivist.com/keycaps/7e0a834c.jpg","name":"Valkyrie","isCover":false,"note":""},{"id":"3d338e07","img":"https://cdn.keycap-archivist.com/keycaps/3d338e07.jpg","name":"Moana Siren","isCover":false,"note":""},{"id":"9b4ee662","img":"https://cdn.keycap-archivist.com/keycaps/9b4ee662.jpg","name":"Taegeukgi","isCover":false,"note":""},{"id":"59e30f19","img":"https://cdn.keycap-archivist.com/keycaps/59e30f19.jpg","name":"Hyperfuse","isCover":false,"note":""},{"id":"aefda4d4","img":"https://cdn.keycap-archivist.com/keycaps/aefda4d4.jpg","name":"Hammerkaze","isCover":false,"note":""},{"id":"5ffc6f12","img":"https://cdn.keycap-archivist.com/keycaps/5ffc6f12.jpg","name":"Grim Stroke","isCover":false,"note":""},{"id":"ac0a4187","img":"https://cdn.keycap-archivist.com/keycaps/ac0a4187.jpg","name":"Cocoa Prince","isCover":false,"giveaway":true,"note":""},{"id":"6a21233a","img":"https://cdn.keycap-archivist.com/keycaps/6a21233a.jpg","name":"Toxic","isCover":false,"totalCount":"1","note":""}]},{"id":"c58bb9e0","name":"Hayabusa","colorways":[{"id":"f7a5e955","img":"https://cdn.keycap-archivist.com/keycaps/f7a5e955.jpg","name":"Beyond Pyramids - Anubis","isCover":false,"note":""},{"id":"1a9b2f37","img":"https://cdn.keycap-archivist.com/keycaps/1a9b2f37.jpg","name":"Beyond Pyramids - Ra","isCover":false,"note":""},{"id":"cf942fad","img":"https://cdn.keycap-archivist.com/keycaps/cf942fad.jpg","name":"Beyond Pyramids - Osiris","isCover":false,"note":""},{"id":"911bb680","img":"https://cdn.keycap-archivist.com/keycaps/911bb680.jpg","name":"Ghost of Spartan","isCover":false,"note":""},{"id":"3f7cb7eb","img":"https://cdn.keycap-archivist.com/keycaps/3f7cb7eb.jpg","name":"The Elder One","isCover":false,"note":""},{"id":"12e06774","img":"https://cdn.keycap-archivist.com/keycaps/12e06774.jpg","name":"Retro","isCover":false,"note":""},{"id":"fadb1169","img":"https://cdn.keycap-archivist.com/keycaps/fadb1169.jpg","name":"Coral","isCover":false,"note":""},{"id":"43f2009b","img":"https://cdn.keycap-archivist.com/keycaps/43f2009b.jpg","name":"Botanic","isCover":false,"note":""},{"id":"3a0f2f6e","img":"https://cdn.keycap-archivist.com/keycaps/3a0f2f6e.jpg","name":"Lotus","isCover":false,"note":""},{"id":"cdd9d79a","img":"https://cdn.keycap-archivist.com/keycaps/cdd9d79a.jpg","name":"Seribusa","isCover":false,"note":""},{"id":"8b3e0ed1","img":"https://cdn.keycap-archivist.com/keycaps/8b3e0ed1.jpg","name":"Carbobusa","isCover":false,"note":""},{"id":"b291db67","img":"https://cdn.keycap-archivist.com/keycaps/b291db67.jpg","name":"Hyperbusa","isCover":false,"note":""},{"id":"dd942a9c","img":"https://cdn.keycap-archivist.com/keycaps/dd942a9c.jpg","name":"Taro","isCover":false,"note":""},{"id":"1d6e93b0","img":"https://cdn.keycap-archivist.com/keycaps/1d6e93b0.jpg","name":"Terminal","isCover":false,"note":""},{"id":"38151043","img":"https://cdn.keycap-archivist.com/keycaps/38151043.jpg","name":"8008","isCover":false,"note":""},{"id":"8c4cf269","img":"https://cdn.keycap-archivist.com/keycaps/8c4cf269.jpg","name":"Split","isCover":false,"note":""},{"id":"858a1c9a","img":"https://cdn.keycap-archivist.com/keycaps/858a1c9a.jpg","name":"Olivia","isCover":false,"note":""},{"id":"96f9ebb5","img":"https://cdn.keycap-archivist.com/keycaps/96f9ebb5.jpg","name":"Ranger","isCover":false,"giveaway":true,"note":""},{"id":"10c2f3c5","img":"https://cdn.keycap-archivist.com/keycaps/10c2f3c5.jpg","name":"Tentacle","isCover":false,"note":""},{"id":"409e567d","img":"https://cdn.keycap-archivist.com/keycaps/409e567d.jpg","name":"Scarlet","isCover":false,"note":""},{"id":"a77cbe4c","img":"https://cdn.keycap-archivist.com/keycaps/a77cbe4c.jpg","name":"Indigo","isCover":false,"note":""},{"id":"e331989e","img":"https://cdn.keycap-archivist.com/keycaps/e331989e.jpg","name":"Batbusa","isCover":false,"note":""},{"id":"55686f3e","img":"https://cdn.keycap-archivist.com/keycaps/55686f3e.jpg","name":"Jokbusa","isCover":false,"note":""},{"id":"6f58eadc","img":"https://cdn.keycap-archivist.com/keycaps/6f58eadc.jpg","name":"Harbusa","isCover":false,"note":""},{"id":"dad1c0f7","img":"https://cdn.keycap-archivist.com/keycaps/dad1c0f7.jpg","name":"Infinity Stones - Soul","isCover":false,"note":""},{"id":"7bb844aa","img":"https://cdn.keycap-archivist.com/keycaps/7bb844aa.jpg","name":"Infinity Stones - Reality","isCover":false,"note":""},{"id":"13caa9cf","img":"https://cdn.keycap-archivist.com/keycaps/13caa9cf.jpg","name":"Infinity Stones - Time","isCover":false,"note":""},{"id":"cbab1c81","img":"https://cdn.keycap-archivist.com/keycaps/cbab1c81.jpg","name":"Infinity Stones - Space","isCover":false,"note":""},{"id":"c9d59723","img":"https://cdn.keycap-archivist.com/keycaps/c9d59723.jpg","name":"Infinity Stones - Power","isCover":false,"note":""},{"id":"69212743","img":"https://cdn.keycap-archivist.com/keycaps/69212743.jpg","name":"Infinity Stones - Mind","isCover":false,"note":""},{"id":"31d5255f","img":"https://cdn.keycap-archivist.com/keycaps/31d5255f.jpg","name":"Amazon","isCover":false,"note":""},{"id":"168c7d64","img":"https://cdn.keycap-archivist.com/keycaps/168c7d64.jpg","name":"Origin","isCover":false,"note":""},{"id":"2b33c641","img":"https://cdn.keycap-archivist.com/keycaps/2b33c641.jpg","name":"Dust","isCover":false,"note":""}]},{"id":"a7f0eea2","name":"Windbreaker","colorways":[{"id":"53369b71","img":"https://cdn.keycap-archivist.com/keycaps/53369b71.jpg","name":"Ember","isCover":false,"note":""},{"id":"74eaddba","img":"https://cdn.keycap-archivist.com/keycaps/74eaddba.jpg","name":"Metal","isCover":false,"note":""},{"id":"80217816","img":"https://cdn.keycap-archivist.com/keycaps/80217816.jpg","name":"Mystique","isCover":false,"note":""},{"id":"377aa1bd","img":"https://cdn.keycap-archivist.com/keycaps/377aa1bd.jpg","name":"Olivia","isCover":false,"note":""}]},{"id":"589e5ed1","name":"Suika","colorways":[{"id":"fa498493","img":"https://cdn.keycap-archivist.com/keycaps/fa498493.jpg","name":"Camping","isCover":false,"note":""},{"id":"47dcd0a2","img":"https://cdn.keycap-archivist.com/keycaps/47dcd0a2.jpg","name":"First Meet","isCover":false,"note":""},{"id":"970744a3","img":"https://cdn.keycap-archivist.com/keycaps/970744a3.jpg","name":"Metropolis","isCover":false,"note":""},{"id":"6eac5945","img":"https://cdn.keycap-archivist.com/keycaps/6eac5945.jpg","name":"Taro","isCover":false,"note":""},{"id":"7d7c70c2","img":"https://cdn.keycap-archivist.com/keycaps/7d7c70c2.jpg","name":"Carbon","isCover":false,"note":""},{"id":"acae6b9e","img":"https://cdn.keycap-archivist.com/keycaps/acae6b9e.jpg","name":"Metro (v1)","isCover":false,"note":""},{"id":"9c19cf7","img":"https://cdn.keycap-archivist.com/keycaps/9c19cf7.jpg","name":"Invaders","isCover":false,"note":""},{"id":"40b96340","img":"https://cdn.keycap-archivist.com/keycaps/40b96340.jpg","name":"Oblivion","isCover":false,"note":""},{"id":"92619e90","img":"https://cdn.keycap-archivist.com/keycaps/92619e90.jpg","name":"Candy Kitty","isCover":false,"giveaway":true,"note":""}]},{"id":"9a79b167","name":"Sumo","colorways":[{"id":"4c10e471","img":"https://cdn.keycap-archivist.com/keycaps/4c10e471.jpg","name":"First Meet","isCover":false,"note":""},{"id":"dce04d43","img":"https://cdn.keycap-archivist.com/keycaps/dce04d43.jpg","name":"Metropolis","isCover":false,"note":""},{"id":"27ea6668","img":"https://cdn.keycap-archivist.com/keycaps/27ea6668.jpg","name":"Carbon","isCover":false,"note":""},{"id":"4072020b","img":"https://cdn.keycap-archivist.com/keycaps/4072020b.jpg","name":"Invaders (Laser)","isCover":false,"note":""},{"id":"6ab39c56","img":"https://cdn.keycap-archivist.com/keycaps/6ab39c56.jpg","name":"Oblivion","isCover":false,"note":""}]},{"id":"ef79a4ca","name":"Minotaurs","colorways":[{"id":"7911ba4e","img":"https://cdn.keycap-archivist.com/keycaps/7911ba4e.jpg","name":"RedNose","isCover":false,"note":""},{"id":"701f76ff","img":"https://cdn.keycap-archivist.com/keycaps/701f76ff.jpg","name":"Tokyo Night","isCover":false,"note":""},{"id":"592acfd0","img":"https://cdn.keycap-archivist.com/keycaps/592acfd0.jpg","name":"Jokertaur","isCover":false,"note":""},{"id":"b804fe06","img":"https://cdn.keycap-archivist.com/keycaps/b804fe06.jpg","name":"Bloodline","isCover":false,"totalCount":"1","note":""}]},{"id":"b9e82627","name":"Melonaurus Fossil","colorways":[{"id":"7c2b422","img":"https://cdn.keycap-archivist.com/keycaps/7c2b422.jpg","name":"Carbon","isCover":false,"note":""},{"id":"a9452f00","img":"https://cdn.keycap-archivist.com/keycaps/a9452f00.jpg","name":"Hammerhead","isCover":false,"note":""},{"id":"1be885ea","img":"https://cdn.keycap-archivist.com/keycaps/1be885ea.jpg","name":"Laser","isCover":false,"note":""},{"id":"48343a3a","img":"https://cdn.keycap-archivist.com/keycaps/48343a3a.jpg","name":"Olivia","isCover":false,"note":""},{"id":"85fe511b","img":"https://cdn.keycap-archivist.com/keycaps/85fe511b.jpg","name":"Samurai","isCover":false,"note":""},{"id":"8d19bd5c","img":"https://cdn.keycap-archivist.com/keycaps/8d19bd5c.jpg","name":"Serika","isCover":false,"note":""}]},{"id":"8e396595","name":"Odin","colorways":[{"id":"e0b89383","img":"https://cdn.keycap-archivist.com/keycaps/e0b89383.jpg","name":"HFO","isCover":false,"note":""}]},{"id":"7c2c36b5","name":"Spiky","colorways":[{"id":"44858cd7","img":"https://cdn.keycap-archivist.com/keycaps/44858cd7.jpg","name":"Atomic","isCover":false,"totalCount":"1","note":""}]},{"id":"ac2db02","name":"Aviator","colorways":[{"id":"dc5deb04","img":"https://cdn.keycap-archivist.com/keycaps/dc5deb04.jpg","name":"","isCover":false,"giveaway":true,"note":""},{"id":"2d042a3f","img":"https://cdn.keycap-archivist.com/keycaps/2d042a3f.jpg","name":"SummerWarp","isCover":false,"note":""},{"id":"b4f07e77","img":"https://cdn.keycap-archivist.com/keycaps/b4f07e77.jpg","name":"MetroMan","isCover":false,"note":""},{"id":"a60dd049","img":"https://cdn.keycap-archivist.com/keycaps/a60dd049.jpg","name":"Phantom","isCover":false,"note":""}]},{"id":"629c7b2e","name":"Aviator v2","colorways":[{"id":"74f78dcf","img":"https://cdn.keycap-archivist.com/keycaps/74f78dcf.jpg","name":"Christmas","isCover":false,"note":""},{"id":"4ab529d7","img":"https://cdn.keycap-archivist.com/keycaps/4ab529d7.jpg","name":"Bloody","isCover":false,"giveaway":true,"note":""}]},{"id":"fa36383","name":"Mr.UtUt","colorways":[{"id":"5aa354c4","img":"https://cdn.keycap-archivist.com/keycaps/5aa354c4.jpg","name":"Christmas","isCover":false,"note":""},{"id":"d6e50d0f","img":"https://cdn.keycap-archivist.com/keycaps/d6e50d0f.jpg","name":"Blue Pill","isCover":false,"note":""},{"id":"ffa8c48d","img":"https://cdn.keycap-archivist.com/keycaps/ffa8c48d.jpg","name":"Seriblack","isCover":false,"note":""},{"id":"7e843bdd","img":"https://cdn.keycap-archivist.com/keycaps/7e843bdd.jpg","name":"Serigrey","isCover":false,"note":""},{"id":"e6c23bf4","img":"https://cdn.keycap-archivist.com/keycaps/e6c23bf4.jpg","name":"Soju","isCover":false,"note":""}]},{"id":"643885ed","name":"NitroSquad - Boy","colorways":[{"id":"ff6565dd","img":"https://cdn.keycap-archivist.com/keycaps/ff6565dd.jpg","name":"Christmas","isCover":false,"note":""}]},{"id":"987e31f5","name":"NitroSquad - Girl","colorways":[{"id":"aa1a0e03","img":"https://cdn.keycap-archivist.com/keycaps/aa1a0e03.jpg","name":"Christmas","isCover":false,"note":""}]},{"id":"aa395a06","name":"Hurricane","colorways":[{"id":"7b41b3b9","img":"https://cdn.keycap-archivist.com/keycaps/7b41b3b9.jpg","name":"Christmas","isCover":false,"note":""}]}],"selfOrder":false,"nationality":"vn"}