{"src":"https://docs.google.com/document/d/1RWKUmcfE9XYslR5GDldajorjTxCqBVM0UE7wBxeB6G4","id":"2f6b5457","name":"Object.Garage","instagram":"https://www.instagram.com/object.garage/","website":"","discord":"","sculpts":[{"id":"74eb6da0","name":"DisCat","colorways":[{"id":"b95afce1","img":"https://cdn.keycap-archivist.com/keycaps/b95afce1.jpg","name":"B & W","isCover":false,"note":""},{"id":"ca2651e9","img":"https://cdn.keycap-archivist.com/keycaps/ca2651e9.jpg","name":"Choco Banana","isCover":false,"note":""},{"id":"3a6954f6","img":"https://cdn.keycap-archivist.com/keycaps/3a6954f6.jpg","name":"Red Chili","isCover":false,"note":""},{"id":"947a00db","img":"https://cdn.keycap-archivist.com/keycaps/947a00db.jpg","name":"Hyper","isCover":false,"note":""},{"id":"396aca15","img":"https://cdn.keycap-archivist.com/keycaps/396aca15.jpg","name":"Choco","isCover":false,"note":""},{"id":"d72e2810","img":"https://cdn.keycap-archivist.com/keycaps/d72e2810.jpg","name":"Blossom","isCover":false,"note":""}]}],"selfOrder":false}